[1,0,0,[["cc.JsonAsset",["_name","json"],1]],[[0,0,1,3]],[[0,"future8",{"#comment":"Future Prototype","version":1,"objects":[{"objclass":"LevelDefinition","objdata":{"CompletionAchievement":"prime_mover","Description":"[PLAYERS_TRIP_TO_FUTURE]","FirstIntroNarrative":"FUTURE_INTRO_GARGANTUAR","FirstRewardParam":"worldkey","FirstRewardType":"worldtrophy","ForceToWorldMap":true,"LevelNumber":8,"Loot":"RTID(DefaultLoot@LevelModules)","MusicType":"MiniGame_A","Name":"[FUTURE_LEVEL_NAME]","NormalPresentTable":"future_normal_01","ShinyPresentTable":"future_shiny_01","StageModule":"RTID(FutureNightStage@LevelModules)","Modules":["RTID(StandardIntro@LevelModules)","RTID(ConveyorBelt@CurrentLevel)","RTID(DefaultZombieWinCondition@LevelModules)","RTID(ZombiesDeadWinCon@LevelModules)","RTID(FutureLinkedTileGroups@CurrentLevel)","RTID(NewWaves@CurrentLevel)","RTID(ChallengeModule@CurrentLevel)"]}},{"objclass":"ConveyorSeedBankProperties","aliases":["ConveyorBelt"],"objdata":{"DropDelayConditions":[{"Delay":3,"MaxPackets":0},{"Delay":6,"MaxPackets":2},{"Delay":9,"MaxPackets":4},{"Delay":12,"MaxPackets":8}],"InitialPlantList":[{"MaxCount":1,"MaxWeightFactor":0,"PlantType":"blover","Weight":150},{"MaxCount":5,"MaxWeightFactor":0,"PlantType":"citron","Weight":50},{"MaxCount":15,"MaxWeightFactor":0,"PlantType":"laser_bean","Weight":150},{"MaxCount":5,"MaxWeightFactor":0,"PlantType":"snapdragon","Weight":100},{"MaxCount":5,"MaxWeightFactor":0,"PlantType":"wallnut","Weight":100}],"SpeedConditions":[{"MaxPackets":0,"Speed":100}]}},{"objclass":"PowerTileProperties","aliases":["FutureLinkedTileGroups"],"objdata":{"LinkedTiles":[]}},{"objclass":"StarChallengeModuleProperties","aliases":["ChallengeModule"],"objdata":{"ChallengesAlwaysAvailable":true,"Challenges":[["RTID(BeatTheLevel@CurrentLevel)","RTID(SaveMowers@LevelModules)"]]}},{"objclass":"StarChallengeBeatTheLevelProps","aliases":["BeatTheLevel"],"objdata":{"Description":"[STARCHALLENGE_FUTURE_FINALE]","DescriptiveName":"[STARCHALLENGE_FUTURE_FINALE_NAME]"}},{"objclass":"WaveManagerModuleProperties","aliases":["NewWaves"],"objdata":{"WaveManagerProps":"RTID(WaveManagerProps@CurrentLevel)","DynamicZombies":[{"PointIncrementPerWave":-40,"StartingPoints":-100,"StartingWave":3,"ZombiePool":["RTID(future@ZombieTypes)","RTID(future_armor1@ZombieTypes)","RTID(future_armor2@ZombieTypes)","RTID(future_jetpack@ZombieTypes)","RTID(future_protector@ZombieTypes)","RTID(mech_cone@ZombieTypes)"]},{"PointIncrementPerWave":-25,"StartingPoints":-100,"StartingWave":4,"ZombiePool":["RTID(future@ZombieTypes)","RTID(future_armor1@ZombieTypes)","RTID(future_armor2@ZombieTypes)","RTID(future_jetpack@ZombieTypes)","RTID(future_protector@ZombieTypes)","RTID(mech_cone@ZombieTypes)"]},{"PointIncrementPerWave":-10,"StartingPoints":-100,"StartingWave":5,"ZombiePool":["RTID(future@ZombieTypes)","RTID(future_armor1@ZombieTypes)","RTID(future_armor2@ZombieTypes)","RTID(future_jetpack@ZombieTypes)","RTID(future_protector@ZombieTypes)","RTID(mech_cone@ZombieTypes)"]},{},{"PointIncrementPerWave":20,"StartingPoints":100,"StartingWave":5,"ZombiePool":["RTID(future@ZombieTypes)","RTID(future_armor1@ZombieTypes)","RTID(future_armor2@ZombieTypes)","RTID(future_jetpack@ZombieTypes)","RTID(future_protector@ZombieTypes)","RTID(mech_cone@ZombieTypes)"]},{"PointIncrementPerWave":40,"StartingPoints":200,"StartingWave":4,"ZombiePool":["RTID(future_armor1@ZombieTypes)","RTID(future_armor2@ZombieTypes)","RTID(future_jetpack@ZombieTypes)","RTID(future_protector@ZombieTypes)","RTID(mech_cone@ZombieTypes)"]},{"PointIncrementPerWave":60,"StartingPoints":400,"StartingWave":3,"ZombiePool":["RTID(future_armor2@ZombieTypes)","RTID(future_jetpack@ZombieTypes)","RTID(future_protector@ZombieTypes)","RTID(mech_cone@ZombieTypes)"]}]}},{"objclass":"WaveManagerProperties","aliases":["WaveManagerProps"],"objdata":{"FlagWaveInterval":9,"WaveCount":18,"WaveSpendingPointIncrement":75,"WaveSpendingPoints":200,"Waves":[["RTID(Wave1@CurrentLevel)"],["RTID(Wave2@CurrentLevel)"],["RTID(Wave3@CurrentLevel)","RTID(Wave3ModConveyor0@CurrentLevel)"],["RTID(Wave4@CurrentLevel)"],["RTID(Wave5@CurrentLevel)"],["RTID(Wave6@CurrentLevel)"],["RTID(Wave7@CurrentLevel)"],["RTID(Wave8@CurrentLevel)"],["RTID(Wave9@CurrentLevel)","RTID(Wave9SpiderRainEvent0@CurrentLevel)"],["RTID(Wave10@CurrentLevel)"],["RTID(Wave11@CurrentLevel)"],["RTID(Wave12@CurrentLevel)"],["RTID(Wave13@CurrentLevel)"],["RTID(Wave14@CurrentLevel)","RTID(Wave14SpiderRainEvent0@CurrentLevel)"],["RTID(Wave15@CurrentLevel)"],["RTID(Wave16@CurrentLevel)"],["RTID(Wave17@CurrentLevel)"],["RTID(Wave18@CurrentLevel)","RTID(Wave18SpiderRainEvent0@CurrentLevel)"]]}},{"objclass":"SpawnZombiesJitteredWaveActionProps","aliases":["Wave1"],"objdata":{"Zombies":[{"Type":"RTID(future_armor1@ZombieTypes)"}]}},{"objclass":"SpawnZombiesJitteredWaveActionProps","aliases":["Wave2"],"objdata":{"Zombies":[{"Type":"RTID(future_jetpack@ZombieTypes)"},{"Type":"RTID(future_armor1@ZombieTypes)"}]}},{"objclass":"SpawnZombiesJitteredWaveActionProps","aliases":["Wave3"],"objdata":{"Zombies":[{"Type":"RTID(future_armor1@ZombieTypes)"},{"Type":"RTID(future_jetpack@ZombieTypes)"}]}},{"objclass":"SpawnZombiesJitteredWaveActionProps","aliases":["Wave4"],"objdata":{"AdditionalPlantfood":1,"DynamicPlantfood":[1,1,1,1,1,1,1],"Zombies":[{"Type":"RTID(future_armor2@ZombieTypes)"},{"Type":"RTID(future@ZombieTypes)"}]}},{"objclass":"SpawnZombiesJitteredWaveActionProps","aliases":["Wave5"],"objdata":{"Zombies":[{"Row":"4","Type":"RTID(future_protector@ZombieTypes)"},{"Row":"5","Type":"RTID(future_armor1@ZombieTypes)"},{"Row":"3","Type":"RTID(future_armor1@ZombieTypes)"}]}},{"objclass":"SpawnZombiesJitteredWaveActionProps","aliases":["Wave6"],"objdata":{"AdditionalPlantfood":1,"DynamicPlantfood":[1,1,1,1,1,0,0],"Zombies":[{"Row":"2","Type":"RTID(mech_cone@ZombieTypes)"},{"Row":"1","Type":"RTID(mech_cone@ZombieTypes)"}]}},{"objclass":"SpawnZombiesJitteredWaveActionProps","aliases":["Wave7"],"objdata":{"Zombies":[{"Row":"1","Type":"RTID(future_jetpack@ZombieTypes)"},{"Row":"2","Type":"RTID(future_jetpack@ZombieTypes)"},{"Row":"3","Type":"RTID(future_jetpack@ZombieTypes)"},{"Row":"4","Type":"RTID(future_jetpack@ZombieTypes)"},{"Row":"5","Type":"RTID(future_jetpack@ZombieTypes)"}]}},{"objclass":"SpawnZombiesJitteredWaveActionProps","aliases":["Wave8"],"objdata":{"AdditionalPlantfood":1,"DynamicPlantfood":[1,1,1,1,1,1,1],"Zombies":[{"Row":"2","Type":"RTID(future_protector@ZombieTypes)"},{"Row":"1","Type":"RTID(future_armor2@ZombieTypes)"},{"Row":"3","Type":"RTID(future_armor2@ZombieTypes)"}]}},{"objclass":"SpawnZombiesJitteredWaveActionProps","aliases":["Wave9"],"objdata":{"AdditionalPlantfood":0,"Zombies":[{"Row":"5","Type":"RTID(mech_cone@ZombieTypes)"},{"Row":"4","Type":"RTID(mech_cone@ZombieTypes)"},{"Row":"1","Type":"RTID(future_jetpack@ZombieTypes)"},{"Row":"2","Type":"RTID(future_jetpack@ZombieTypes)"},{"Row":"3","Type":"RTID(future_jetpack@ZombieTypes)"},{"Row":"4","Type":"RTID(future_jetpack@ZombieTypes)"},{"Row":"5","Type":"RTID(future_jetpack@ZombieTypes)"}]}},{"objclass":"SpawnZombiesJitteredWaveActionProps","aliases":["Wave10"],"objdata":{"Zombies":[{"Type":"RTID(future_armor1@ZombieTypes)"},{"Type":"RTID(future@ZombieTypes)"},{"Type":"RTID(future_armor1@ZombieTypes)"},{"Type":"RTID(future@ZombieTypes)"}]}},{"objclass":"SpawnZombiesJitteredWaveActionProps","aliases":["Wave11"],"objdata":{"AdditionalPlantfood":1,"DynamicPlantfood":[1,1,1,1,0,1,1],"Zombies":[{"Type":"RTID(future_gargantuar@ZombieTypes)"}]}},{"objclass":"SpawnZombiesJitteredWaveActionProps","aliases":["Wave12"],"objdata":{"AdditionalPlantfood":0,"Zombies":[{"Row":"4","Type":"RTID(future_protector@ZombieTypes)"},{"Row":"2","Type":"RTID(future_protector@ZombieTypes)"},{"Row":"1","Type":"RTID(future_armor1@ZombieTypes)"},{"Row":"5","Type":"RTID(future_armor1@ZombieTypes)"},{"Row":"3","Type":"RTID(future_armor1@ZombieTypes)"}]}},{"objclass":"SpawnZombiesJitteredWaveActionProps","aliases":["Wave13"],"objdata":{"AdditionalPlantfood":1,"DynamicPlantfood":[1,1,1,1,1,1,0],"Zombies":[{"Type":"RTID(future@ZombieTypes)"},{"Type":"RTID(future_armor1@ZombieTypes)"},{"Type":"RTID(future_armor2@ZombieTypes)"},{"Row":"3","Type":"RTID(future_jetpack@ZombieTypes)"},{"Row":"1","Type":"RTID(future_jetpack@ZombieTypes)"},{"Row":"2","Type":"RTID(future_jetpack@ZombieTypes)"},{"Row":"4","Type":"RTID(future_jetpack@ZombieTypes)"},{"Row":"5","Type":"RTID(future_jetpack@ZombieTypes)"}]}},{"objclass":"SpawnZombiesJitteredWaveActionProps","aliases":["Wave14"],"objdata":{"Zombies":[{"Row":"1","Type":"RTID(mech_cone@ZombieTypes)"},{"Row":"3","Type":"RTID(mech_cone@ZombieTypes)"},{"Row":"5","Type":"RTID(mech_cone@ZombieTypes)"}]}},{"objclass":"SpawnZombiesJitteredWaveActionProps","aliases":["Wave15"],"objdata":{"AdditionalPlantfood":1,"DynamicPlantfood":[1,1,1,1,1,1,1],"Zombies":[{"Type":"RTID(future@ZombieTypes)"},{"Type":"RTID(future@ZombieTypes)"},{"Type":"RTID(future_armor1@ZombieTypes)"},{"Type":"RTID(future_armor1@ZombieTypes)"},{"Type":"RTID(future_armor2@ZombieTypes)"},{"Type":"RTID(future_armor2@ZombieTypes)"},{"Type":"RTID(future_jetpack@ZombieTypes)"},{"Type":"RTID(future_jetpack@ZombieTypes)"}]}},{"objclass":"SpawnZombiesJitteredWaveActionProps","aliases":["Wave16"],"objdata":{"AdditionalPlantfood":1,"DynamicPlantfood":[1,1,1,1,1,0,0],"Zombies":[{"Row":"3","Type":"RTID(future_protector@ZombieTypes)"},{"Row":"4","Type":"RTID(future_armor2@ZombieTypes)"},{"Row":"2","Type":"RTID(future_armor2@ZombieTypes)"},{"Row":"1","Type":"RTID(future_protector@ZombieTypes)"},{"Row":"5","Type":"RTID(future_protector@ZombieTypes)"}]}},{"objclass":"SpawnZombiesJitteredWaveActionProps","aliases":["Wave17"],"objdata":{"AdditionalPlantfood":1,"DynamicPlantfood":[1,1,1,1,1,1,1],"Zombies":[{"Row":"1","Type":"RTID(future_jetpack@ZombieTypes)"},{"Row":"1","Type":"RTID(future_jetpack@ZombieTypes)"},{"Type":"RTID(mech_cone@ZombieTypes)"},{"Row":"2","Type":"RTID(future_jetpack@ZombieTypes)"},{"Row":"2","Type":"RTID(future_jetpack@ZombieTypes)"},{"Row":"3","Type":"RTID(future_jetpack@ZombieTypes)"},{"Row":"3","Type":"RTID(future_jetpack@ZombieTypes)"},{"Row":"4","Type":"RTID(future_jetpack@ZombieTypes)"},{"Row":"4","Type":"RTID(future_jetpack@ZombieTypes)"},{"Row":"5","Type":"RTID(future_jetpack@ZombieTypes)"},{"Row":"5","Type":"RTID(future_jetpack@ZombieTypes)"}]}},{"objclass":"SpawnZombiesJitteredWaveActionProps","aliases":["Wave18"],"objdata":{"Zombies":[{"Type":"RTID(future_gargantuar@ZombieTypes)"},{"Type":"RTID(future_gargantuar@ZombieTypes)"}]}},{"objclass":"SpiderRainZombieSpawnerProps","aliases":["Wave9SpiderRainEvent0"],"objdata":{"ColumnEnd":9,"ColumnStart":6,"GroupSize":1,"SpiderCount":5,"SpiderZombieName":"future_imp","TimeBeforeFullSpawn":2,"TimeBetweenGroups":0.25,"WaveStartMessage":"[WARNING_SPIDERRAIN]","ZombieFallTime":1.5}},{"objclass":"SpiderRainZombieSpawnerProps","aliases":["Wave14SpiderRainEvent0"],"objdata":{"ColumnEnd":8,"ColumnStart":5,"GroupSize":1,"SpiderCount":5,"SpiderZombieName":"future_imp","TimeBeforeFullSpawn":2,"TimeBetweenGroups":0.25,"WaveStartMessage":"[WARNING_SPIDERRAIN]","ZombieFallTime":1.5}},{"objclass":"SpiderRainZombieSpawnerProps","aliases":["Wave18SpiderRainEvent0"],"objdata":{"ColumnEnd":7,"ColumnStart":4,"GroupSize":1,"SpiderCount":5,"SpiderZombieName":"future_imp","TimeBeforeFullSpawn":2,"TimeBetweenGroups":0.25,"WaveStartMessage":"[WARNING_SPIDERRAIN]","ZombieFallTime":1.5}},{"objclass":"ModifyConveyorWaveActionProps","aliases":["Wave3ModConveyor0"],"objdata":{"Add":[{"MaxCount":3,"MaxWeightFactor":0,"MinWeightFactor":0.1,"ToolType":"tool_powertile_alpha","Weight":50},{"MaxCount":3,"MaxWeightFactor":0,"MinWeightFactor":0.1,"ToolType":"tool_powertile_beta","Weight":50}],"Remove":[]}}]}]],0,0,[],[],[]]
