[1,["56Yc/fVrZJRaoqb4hcC1Sa","7bVGJDivNNXpTp8uyVkS3s","bdbvNtapZIsp8ImB8bbcYP","b0vKi/Q81JT51rjWiG2jEW","04itm9LU1BT5WVYL/x7Qdf","3a/pRBSatKkaibfGdC8dFq","23DR+h8BBP3KmnhaHpaQW8","34Pp9UxXlP9JwZ0iPeYX7r@6c48a"],["node","root","data","_dragonAsset","_dragonAtlasAsset","BG","_texture"],[["cc.AudioClip",["_name","_native","_duration"],0],["cc.Prefab",["_name"],2],["cc.Node",["_name","_components","_prefab"],2,9,4],["cc.UITransform",["node","__prefab","_contentSize"],3,1,4,5],["cc.CompPrefabInfo",["fileId"],2],["dragonBones.ArmatureDisplay",["_defaultArmatureIndexValue","_armatureName","_animationName","_enableBatch","node","__prefab","_dragonAsset","_dragonAtlasAsset"],-1,1,4,6,6],["2eaf2NpCFxDw4YLW30aax6G",["isModern","IdleAnmList","node","__prefab","soundEvents","validSize","BG"],1,1,4,9,5,6],["SoundPlayEvent",["eventName","cdByClipDuration","volume","clips"],0,3],["cc.PrefabInfo",["fileId","instance","targetOverrides","nestedPrefabInstanceRoots","root","asset"],-1,1,1],["4c2fccq7FZO2IEkVgOAvEZ1",["IdleAnmList","node","__prefab"],2,1,4],["dragonBones.DragonBonesAsset",["_name","_dragonBonesJson"],1],["dragonBones.DragonBonesAtlasAsset",["_name","_atlasJson","_atlasJsonData"],0]],[[4,0,2],[0,0,1,2,4],[1,0,2],[2,0,1,2,2],[3,0,1,2,1],[5,0,1,2,3,4,5,6,7,5],[7,0,1,2,3,4],[8,0,1,2,3,4,5,5],[6,0,1,2,3,4,5,6,3],[9,0,1,2,2],[10,0,1,3],[11,0,1,2,4]],[[[[1,"move0",".mp3",0.54],-1],0,0,[],[],[]],[[[2,"SliderUpModernTILE"],[3,"SliderUpModernTILE",[[4,-2,[0,"71dGHfuQpNm4Ho981Ozjzw"],[5,72,99]],[5,0,"Up_U","Idle",true,-3,[0,"94MDbnIqBMcKed2CZFNpQt"],0,1],[8,true,["Idle"],-4,[0,"5c9LY96htOX6h2Z6SPBfTL"],[[6,"splash",0.3,2,[2,3]],[6,"move",0.3,0.3,[4,5]]],[0,187.5,215],6]],[7,"c46/YsCPVOJYA4mWEpNYRx",null,null,null,-1,0]]],0,[0,1,1,0,0,1,0,0,1,0,0,1,0,2,1,4],[0,0,0,0,0,0,0],[3,4,-1,-2,-1,-2,5],[0,1,2,3,4,5,6]],[[[2,"SliderModernUpBGTILE"],[3,"SliderModernUpBGTILE",[[4,-2,[0,"71dGHfuQpNm4Ho981Ozjzw"],[5,220,220]],[5,6,"Up_D","Idle",true,-3,[0,"94MDbnIqBMcKed2CZFNpQt"],0,1],[9,["Idle"],-4,[0,"451CdlJ6RHKZpgotTSX8F7"]]],[7,"c46/YsCPVOJYA4mWEpNYRx",null,null,null,-1,0]]],0,[0,1,1,0,0,1,0,0,1,0,0,1,0,2,1,4],[0,0],[3,4],[0,1]],[[[1,"move1",".mp3",0.468],-1],0,0,[],[],[]],[[[10,"TileAnimate_ske","{\"frameRate\":30,\"name\":\"TileAnimate\",\"version\":\"5.5\",\"compatibleVersion\":\"5.5\",\"armature\":[{\"type\":\"Armature\",\"frameRate\":30,\"name\":\"Up_U\",\"aabb\":{\"x\":-36.34,\"y\":-51.18,\"width\":72,\"height\":99},\"bone\":[{\"name\":\"root\"},{\"name\":\"main\",\"parent\":\"root\",\"transform\":{\"scX\":1.15,\"scY\":1.15}},{\"length\":49,\"name\":\"back\",\"parent\":\"main\",\"transform\":{\"x\":-2.25,\"y\":52.75}},{\"length\":54,\"name\":\"sinkBottom\",\"parent\":\"main\",\"transform\":{\"x\":-3.45,\"y\":60.1}},{\"name\":\"splash\",\"parent\":\"main\",\"transform\":{\"y\":-38.5676,\"scX\":0.3552,\"scY\":0.3552}},{\"length\":54,\"name\":\"sinkPoint\",\"parent\":\"main\",\"transform\":{\"x\":1.759,\"y\":-43.7188,\"skX\":180,\"skY\":180,\"scX\":0.5138,\"scY\":1.1491}},{\"name\":\"face\",\"parent\":\"main\",\"transform\":{\"x\":-0.2921,\"y\":-1.4606}},{\"name\":\"bottom\",\"parent\":\"back\",\"transform\":{\"y\":-56.8104}},{\"length\":407,\"name\":\"smi\",\"parent\":\"splash\",\"transform\":{\"y\":-1.45,\"skX\":-90,\"skY\":-90,\"scX\":0.7369,\"scY\":0.4691}},{\"length\":129,\"name\":\"sbt\",\"parent\":\"splash\",\"transform\":{\"y\":-8.15,\"skX\":-90.3545,\"skY\":-90.3545,\"scX\":0.5846,\"scY\":0.7667}},{\"name\":\"sbh\",\"parent\":\"splash\",\"transform\":{\"scX\":0.7644,\"scY\":0.7644}},{\"name\":\"bb2\",\"parent\":\"splash\",\"transform\":{\"x\":24.8261,\"y\":-168.3}},{\"length\":302,\"name\":\"smo\",\"parent\":\"splash\",\"transform\":{\"skX\":-90,\"skY\":-90,\"scX\":0.7577,\"scY\":0.7577}},{\"length\":353,\"name\":\"smp\",\"parent\":\"splash\",\"transform\":{\"skX\":-90,\"skY\":-90,\"scX\":0.7416,\"scY\":0.7416}},{\"name\":\"bbsR\",\"parent\":\"splash\",\"transform\":{\"x\":94.35,\"y\":3.25}},{\"name\":\"bb1\",\"parent\":\"splash\",\"transform\":{\"x\":-75.8,\"y\":-148.6}},{\"name\":\"bbsL\",\"parent\":\"splash\",\"transform\":{\"x\":-57.7577,\"y\":9.7211}}],\"slot\":[{\"displayIndex\":-1,\"name\":\"sinkFaceU1\",\"parent\":\"root\"},{\"name\":\"_wvU_U\",\"parent\":\"main\"},{\"displayIndex\":-1,\"name\":\"bottom_U\",\"parent\":\"bottom\"},{\"name\":\"faceU\",\"parent\":\"face\"},{\"displayIndex\":-1,\"name\":\"sinkFaceU\",\"parent\":\"face\"},{\"displayIndex\":-1,\"name\":\"sinkPoint\",\"parent\":\"sinkPoint\"},{\"displayIndex\":-1,\"name\":\"sinkPointSide\",\"parent\":\"sinkPoint\"},{\"displayIndex\":-1,\"name\":\"sinkBottom\",\"parent\":\"sinkBottom\"},{\"displayIndex\":-1,\"name\":\"sinkBottomSide\",\"parent\":\"sinkBottom\"},{\"displayIndex\":-1,\"name\":\"sbt\",\"parent\":\"sbt\"},{\"displayIndex\":-1,\"name\":\"smi\",\"parent\":\"smi\"},{\"displayIndex\":-1,\"name\":\"smo\",\"parent\":\"smo\"},{\"displayIndex\":-1,\"name\":\"smp\",\"parent\":\"smp\"},{\"displayIndex\":-1,\"name\":\"sbh\",\"parent\":\"sbh\"},{\"displayIndex\":-1,\"name\":\"bbsL\",\"parent\":\"bbsL\"},{\"displayIndex\":-1,\"name\":\"bbsR\",\"parent\":\"bbsR\"},{\"displayIndex\":-1,\"name\":\"bb1\",\"parent\":\"bb1\"},{\"displayIndex\":-1,\"name\":\"bb2\",\"parent\":\"bb2\"}],\"skin\":[{\"slot\":[{\"name\":\"smi\",\"display\":[{\"name\":\"s\",\"transform\":{\"x\":188.71,\"y\":-5.69,\"skX\":90,\"skY\":90},\"path\":\"tide/splashMainInner\"}]},{\"name\":\"bb1\",\"display\":[{\"name\":\"s\",\"transform\":{\"x\":2.99,\"y\":3.8},\"path\":\"tide/splash_bubble1\"}]},{\"name\":\"sinkFaceU1\",\"display\":[{\"name\":\"sinkFaceU\",\"transform\":{\"x\":-0.64,\"y\":-3.27,\"skX\":180,\"skY\":180,\"scX\":1.602,\"scY\":1.3233}}]},{\"name\":\"sbh\",\"display\":[{\"name\":\"s\",\"transform\":{\"x\":5.86,\"y\":-52.3},\"path\":\"tide/splash_baseHere\"}]},{\"name\":\"bb2\",\"display\":[{\"name\":\"s\",\"transform\":{\"x\":-3.08,\"y\":3.74},\"path\":\"tide/splash_bubble2\"}]},{\"name\":\"smo\",\"display\":[{\"name\":\"s\",\"transform\":{\"x\":116.88,\"y\":-1.58,\"skX\":90,\"skY\":90},\"path\":\"tide/splashMainOuter\"}]},{\"name\":\"sinkPoint\",\"display\":[{\"name\":\"sinkBottom\",\"transform\":{\"x\":0.18,\"y\":3.28}}]},{\"name\":\"_wvU_U\",\"display\":[{\"type\":\"armature\",\"name\":\"_wvU_U\",\"transform\":{\"scX\":0.7905,\"scY\":0.7905}}]},{\"name\":\"bbsR\",\"display\":[{\"name\":\"s\",\"transform\":{\"x\":5.67,\"y\":-5.27},\"path\":\"tide/splash_bubblesR\"}]},{\"name\":\"smp\",\"display\":[{\"name\":\"s\",\"transform\":{\"x\":179.83,\"y\":0.76,\"skX\":90,\"skY\":90},\"path\":\"tide/splashMainPush\"}]},{\"name\":\"sinkBottom\",\"display\":[{\"name\":\"sinkBottom\",\"transform\":{\"x\":0.18,\"y\":3.28}}]},{\"name\":\"bbsL\",\"display\":[{\"name\":\"s\",\"transform\":{\"x\":-30.06,\"y\":-8.51},\"path\":\"tide/splash_bubblesL\"}]},{\"name\":\"sbt\",\"display\":[{\"name\":\"s\",\"transform\":{\"x\":123.94,\"y\":8.1,\"skX\":90.35,\"skY\":90.35},\"path\":\"tide/splash_baseThere\"}]},{\"name\":\"faceU\",\"display\":[{\"name\":\"faceU\"}]},{\"name\":\"sinkPointSide\",\"display\":[{\"name\":\"sinkBottomSide\",\"transform\":{\"x\":0.86,\"y\":-2.45}}]},{\"name\":\"bottom_U\",\"display\":[{\"name\":\"bottom_U\",\"transform\":{\"x\":2.42,\"y\":2.18}}]},{\"name\":\"sinkBottomSide\",\"display\":[{\"name\":\"sinkBottomSide\",\"transform\":{\"x\":0.86,\"y\":-2.45}}]},{\"name\":\"sinkFaceU\",\"display\":[{\"name\":\"sinkFaceU\"}]}]}],\"animation\":[{\"duration\":100,\"playTimes\":0,\"name\":\"Idle\",\"bone\":[{\"name\":\"face\",\"translateFrame\":[{\"duration\":25,\"curve\":[0,0,0.5,1]},{\"duration\":25,\"curve\":[0.5,0,1,1],\"x\":-2.31,\"y\":-3.15},{\"duration\":25,\"curve\":[0,0,0.5,1]},{\"duration\":25,\"curve\":[0.5,0,1,1],\"x\":1.15,\"y\":3.81},{\"duration\":0}],\"rotateFrame\":[{\"duration\":25,\"curve\":[0,0,0.5,1]},{\"duration\":25,\"curve\":[0.5,0,1,1],\"rotate\":-1.29},{\"duration\":50}],\"scaleFrame\":[{\"duration\":25,\"curve\":[0,0,0.5,1]},{\"duration\":25,\"curve\":[0.5,0,1,1],\"x\":1.01,\"y\":0.97},{\"duration\":25,\"curve\":[0,0,0.5,1]},{\"duration\":25,\"curve\":[0.5,0,1,1],\"x\":0.98,\"y\":1.04},{\"duration\":0}]},{\"name\":\"sinkPoint\",\"scaleFrame\":[{\"duration\":25,\"curve\":[0,0,0.5,1]},{\"duration\":25,\"curve\":[0.5,0,1,1],\"x\":0.99,\"y\":1.1},{\"duration\":25,\"curve\":[0,0,0.5,1]},{\"duration\":25,\"curve\":[0.5,0,1,1],\"x\":0.97,\"y\":1.04},{\"duration\":0}]}]},{\"duration\":37,\"playTimes\":0,\"name\":\"ActiveStart\",\"frame\":[{},{\"events\":[{\"name\":\"splash\"}]},{\"duration\":0,\"events\":[{\"name\":\"move\"}]}],\"bone\":[{\"name\":\"back\",\"translateFrame\":[{\"duration\":6,\"curve\":[0,0,0.5,1]},{\"duration\":7,\"curve\":[0.5,0,0.5,1],\"y\":-44.84},{\"duration\":24,\"y\":-35.82}]},{\"name\":\"face\",\"translateFrame\":[{\"duration\":6,\"curve\":[0,0,0.5,1]},{\"duration\":7,\"curve\":[0.5,0,0.5,1],\"y\":-22.01},{\"duration\":24,\"y\":-17.61}],\"scaleFrame\":[{\"duration\":6,\"curve\":[0,0,0.5,1]},{\"duration\":7,\"curve\":[0.5,0,0.5,1],\"x\":1.14,\"y\":0.53},{\"duration\":24,\"x\":1.08,\"y\":0.61}]},{\"name\":\"bottom\",\"translateFrame\":[{\"duration\":6,\"curve\":[0,0,0.5,1]},{\"duration\":31,\"x\":-1.62,\"y\":29.23}],\"scaleFrame\":[{\"duration\":6,\"curve\":[0,0,0.5,1]},{\"duration\":7,\"tweenEasing\":0,\"x\":1.15,\"y\":0.67},{\"duration\":24,\"x\":1.13,\"y\":0.67}]},{\"name\":\"sinkBottom\",\"scaleFrame\":[{\"duration\":4,\"tweenEasing\":0},{\"duration\":33,\"x\":0.77,\"y\":0.77}]},{\"name\":\"sinkPoint\",\"translateFrame\":[{\"duration\":4,\"tweenEasing\":0},{\"duration\":33,\"y\":-2.86}],\"scaleFrame\":[{\"duration\":4,\"tweenEasing\":0},{\"duration\":33,\"x\":1.65,\"y\":0.73}]},{\"name\":\"sbt\",\"scaleFrame\":[{\"duration\":11,\"curve\":[0,0,0.5,1],\"x\":0.7,\"y\":0.7},{\"duration\":13,\"curve\":[0.5,0,1,1],\"x\":1.73,\"y\":1.02},{\"duration\":13,\"x\":0.99,\"y\":1.51}]},{\"name\":\"sbh\",\"translateFrame\":[{\"duration\":11,\"curve\":[0,0,0.5,1]},{\"duration\":13,\"curve\":[0.5,0,1,1],\"y\":25.45},{\"duration\":13,\"y\":-3.19}],\"scaleFrame\":[{\"duration\":11,\"curve\":[0,0,0.5,1],\"x\":0.7,\"y\":0.7},{\"duration\":13,\"curve\":[0.5,0,1,1],\"y\":2.1},{\"duration\":13,\"x\":1.5,\"y\":0.91}]},{\"name\":\"smi\",\"scaleFrame\":[{\"duration\":13,\"curve\":[0,0,0.5,1],\"x\":0.08,\"y\":0.78},{\"duration\":5,\"curve\":[0,0,0.5,1],\"x\":0.08,\"y\":0.78},{\"duration\":14,\"curve\":[0.5,0,1,1]},{\"duration\":5,\"x\":0.58}]},{\"name\":\"smo\",\"scaleFrame\":[{\"duration\":10,\"curve\":[0,0,0.5,1],\"x\":0.08,\"y\":0.78},{\"duration\":5,\"curve\":[0,0,0.5,1],\"x\":0.08,\"y\":0.78},{\"duration\":17,\"curve\":[0.5,0,1,1]},{\"duration\":5,\"x\":0.58}]},{\"name\":\"smp\",\"scaleFrame\":[{\"duration\":8,\"curve\":[0,0,0.5,1],\"x\":0.08,\"y\":0.78},{\"duration\":5,\"curve\":[0,0,0.5,1],\"x\":0.08,\"y\":0.78},{\"duration\":19,\"curve\":[0.5,0,1,1]},{\"duration\":5,\"x\":0.58}]},{\"name\":\"bbsR\",\"translateFrame\":[{\"duration\":17,\"curve\":[0,0,0.5,1]},{\"duration\":20,\"x\":14.57,\"y\":33.69}],\"scaleFrame\":[{\"duration\":17,\"curve\":[0,0,0.5,1]},{\"duration\":20,\"x\":1.39,\"y\":1.15}]},{\"name\":\"bb1\",\"translateFrame\":[{\"duration\":10},{\"duration\":9,\"curve\":[0,0,0.5,1],\"y\":150.14},{\"duration\":14,\"curve\":[0.5,0,1,1],\"y\":-231.65},{\"duration\":4,\"y\":-112.22}]},{\"name\":\"bb2\",\"translateFrame\":[{\"duration\":14},{\"duration\":9,\"curve\":[0,0,0.5,1],\"y\":150.14},{\"duration\":14,\"curve\":[0.5,0,1,1],\"y\":-231.65},{\"duration\":0,\"y\":-112.22}]},{\"name\":\"bbsL\",\"translateFrame\":[{\"duration\":17,\"curve\":[0,0,0.5,1]},{\"duration\":20,\"x\":-15.48,\"y\":27.31}],\"scaleFrame\":[{\"duration\":17,\"curve\":[0,0,0.5,1]},{\"duration\":20,\"x\":1.39,\"y\":1.15}]}],\"slot\":[{\"name\":\"bottom_U\",\"displayFrame\":[{\"duration\":37}]},{\"name\":\"sinkBottom\",\"colorFrame\":[{\"duration\":4,\"tweenEasing\":0},{\"duration\":33,\"value\":{\"aM\":0}}]},{\"name\":\"sinkBottomSide\",\"colorFrame\":[{\"duration\":4,\"tweenEasing\":0},{\"duration\":33,\"value\":{\"aM\":0}}]},{\"name\":\"sinkPoint\",\"displayFrame\":[{\"duration\":37}]},{\"name\":\"sinkPointSide\",\"displayFrame\":[{\"duration\":37}],\"colorFrame\":[{\"duration\":4,\"tweenEasing\":0,\"value\":{\"aM\":0}},{\"duration\":33}]},{\"name\":\"sbt\",\"displayFrame\":[{\"duration\":37}],\"colorFrame\":[{\"duration\":5,\"tweenEasing\":0,\"value\":{\"aM\":0}},{\"duration\":12,\"tweenEasing\":0},{\"duration\":7,\"tweenEasing\":0},{\"duration\":13,\"value\":{\"aM\":0}}]},{\"name\":\"smi\",\"displayFrame\":[{\"duration\":37}],\"colorFrame\":[{\"duration\":26},{\"duration\":6,\"tweenEasing\":0},{\"duration\":5,\"value\":{\"aM\":0}}]},{\"name\":\"smo\",\"displayFrame\":[{\"duration\":10,\"value\":-1},{\"duration\":27}],\"colorFrame\":[{\"duration\":26},{\"duration\":6,\"tweenEasing\":0},{\"duration\":5,\"value\":{\"aM\":0}}]},{\"name\":\"smp\",\"displayFrame\":[{\"duration\":37}],\"colorFrame\":[{\"duration\":20},{\"duration\":6,\"tweenEasing\":0},{\"duration\":11,\"value\":{\"aM\":0}}]},{\"name\":\"sbh\",\"displayFrame\":[{\"duration\":37}],\"colorFrame\":[{\"duration\":5,\"tweenEasing\":0,\"value\":{\"aM\":0}},{\"duration\":12,\"tweenEasing\":0},{\"duration\":7,\"tweenEasing\":0},{\"duration\":13,\"value\":{\"aM\":0}}]},{\"name\":\"bbsL\",\"displayFrame\":[{\"duration\":37}],\"colorFrame\":[{\"duration\":3,\"curve\":[0,0,0.5,1],\"value\":{\"aM\":0}},{\"duration\":8,\"tweenEasing\":0},{\"duration\":6,\"tweenEasing\":0},{\"duration\":20,\"value\":{\"aM\":0}}]},{\"name\":\"bbsR\",\"displayFrame\":[{\"duration\":37}],\"colorFrame\":[{\"duration\":3,\"curve\":[0,0,0.5,1],\"value\":{\"aM\":0}},{\"duration\":8,\"tweenEasing\":0},{\"duration\":6,\"tweenEasing\":0},{\"duration\":20,\"value\":{\"aM\":0}}]},{\"name\":\"bb1\",\"displayFrame\":[{\"duration\":10,\"value\":-1},{\"duration\":27}],\"colorFrame\":[{\"duration\":26},{\"duration\":7,\"tweenEasing\":0},{\"duration\":4,\"value\":{\"aM\":0}}]},{\"name\":\"bb2\",\"displayFrame\":[{\"duration\":14,\"value\":-1},{\"duration\":23}],\"colorFrame\":[{\"duration\":30},{\"duration\":7,\"tweenEasing\":0},{\"duration\":0,\"value\":{\"aM\":0}}]},{\"name\":\"sinkFaceU1\",\"displayFrame\":[{\"duration\":37}],\"colorFrame\":[{\"duration\":5,\"tweenEasing\":0,\"value\":{\"aM\":0}},{\"duration\":32}]}]},{\"duration\":50,\"playTimes\":0,\"name\":\"ActiveEnd\",\"frame\":[{\"duration\":4},{\"duration\":0,\"events\":[{\"name\":\"splash\"}]}],\"bone\":[{\"name\":\"back\",\"translateFrame\":[{\"duration\":4,\"tweenEasing\":0,\"y\":-35.82},{\"duration\":8,\"curve\":[0,0,0.5,1]},{\"duration\":5,\"curve\":[0.5,0,0.5,1],\"y\":-9.86},{\"duration\":8,\"tweenEasing\":0,\"y\":0.76},{\"duration\":6,\"curve\":[0,0,0.5,1],\"x\":4.55,\"y\":2.27},{\"duration\":19,\"curve\":[0.5,0,0.5,1],\"y\":-8.72},{\"duration\":0}],\"scaleFrame\":[{\"duration\":4},{\"duration\":8,\"curve\":[0,0,0.5,1]},{\"duration\":5,\"curve\":[0.5,0,0.5,1],\"x\":0.83,\"y\":0.75},{\"duration\":8,\"tweenEasing\":0,\"x\":1.08,\"y\":0.92},{\"duration\":6,\"curve\":[0,0,0.5,1],\"x\":1.02,\"y\":0.92},{\"duration\":19,\"curve\":[0.5,0,0.5,1],\"x\":1.02,\"y\":0.92},{\"duration\":0}]},{\"name\":\"face\",\"translateFrame\":[{\"duration\":4,\"tweenEasing\":0,\"y\":-17.61},{\"duration\":13,\"curve\":[0,0,0.5,1]},{\"duration\":8,\"curve\":[0.5,0,1,1],\"y\":-10.62},{\"duration\":6,\"curve\":[0,0,0.5,1],\"x\":3.41,\"y\":6.45},{\"duration\":19,\"curve\":[0.5,0,0.5,1],\"x\":-0.76,\"y\":-6.07},{\"duration\":0}],\"scaleFrame\":[{\"duration\":4,\"tweenEasing\":0,\"x\":1.08,\"y\":0.61},{\"duration\":8,\"curve\":[0,0,0.5,1]},{\"duration\":5,\"curve\":[0.5,0,0.5,1],\"x\":0.83,\"y\":0.83},{\"duration\":8,\"curve\":[0.5,0,1,1],\"x\":1.14,\"y\":1.23},{\"duration\":6,\"curve\":[0,0,0.5,1]},{\"duration\":19,\"curve\":[0.5,0,0.5,1],\"y\":0.93},{\"duration\":0}]},{\"name\":\"bottom\",\"translateFrame\":[{\"duration\":4,\"tweenEasing\":0,\"x\":-1.62,\"y\":29.23},{\"duration\":46}],\"scaleFrame\":[{\"duration\":4,\"tweenEasing\":0,\"x\":1.13,\"y\":0.67},{\"duration\":46}]},{\"name\":\"sinkPoint\",\"translateFrame\":[{\"duration\":4,\"tweenEasing\":0,\"y\":-2.86},{\"duration\":8,\"curve\":[0,0,0.5,1],\"y\":9.78},{\"duration\":5,\"curve\":[0.5,0,0.5,1],\"y\":8.3},{\"duration\":14,\"tweenEasing\":0,\"y\":-9.84},{\"duration\":19,\"y\":-4.91}],\"scaleFrame\":[{\"duration\":4,\"tweenEasing\":0,\"x\":1.65,\"y\":0.73},{\"duration\":8,\"tweenEasing\":0,\"x\":1.45,\"y\":1.13},{\"duration\":5,\"curve\":[0.5,0,0.5,1],\"y\":1.08},{\"duration\":14,\"tweenEasing\":0,\"x\":0.62,\"y\":0.62},{\"duration\":19,\"curve\":[0.5,0,0.5,1],\"x\":0.62,\"y\":0.62},{\"duration\":0}]},{\"name\":\"splash\",\"translateFrame\":[{\"duration\":4},{\"duration\":46,\"y\":84.09}]},{\"name\":\"sbt\",\"scaleFrame\":[{\"duration\":4},{\"duration\":11,\"curve\":[0,0,0.5,1],\"x\":0.7,\"y\":0.7},{\"duration\":13,\"curve\":[0.5,0,1,1],\"x\":1.73,\"y\":1.02},{\"duration\":22,\"x\":0.99,\"y\":1.51}]},{\"name\":\"sbh\",\"translateFrame\":[{\"duration\":4},{\"duration\":11,\"curve\":[0,0,0.5,1]},{\"duration\":13,\"curve\":[0.5,0,1,1],\"y\":25.45},{\"duration\":22,\"y\":-3.19}],\"scaleFrame\":[{\"duration\":4},{\"duration\":11,\"curve\":[0,0,0.5,1],\"x\":0.7,\"y\":0.7},{\"duration\":13,\"curve\":[0.5,0,1,1],\"y\":2.1},{\"duration\":22,\"x\":1.5,\"y\":0.91}]},{\"name\":\"smi\",\"scaleFrame\":[{\"duration\":4},{\"duration\":13,\"curve\":[0,0,0.5,1],\"x\":0.08,\"y\":0.78},{\"duration\":5,\"curve\":[0,0,0.5,1],\"x\":0.08,\"y\":0.78},{\"duration\":14,\"curve\":[0.5,0,1,1]},{\"duration\":14,\"x\":0.58}]},{\"name\":\"smo\",\"scaleFrame\":[{\"duration\":4},{\"duration\":10,\"curve\":[0,0,0.5,1],\"x\":0.08,\"y\":0.78},{\"duration\":5,\"curve\":[0,0,0.5,1],\"x\":0.08,\"y\":0.78},{\"duration\":17,\"curve\":[0.5,0,1,1]},{\"duration\":14,\"x\":0.58}]},{\"name\":\"smp\",\"scaleFrame\":[{\"duration\":4},{\"duration\":8,\"curve\":[0,0,0.5,1],\"x\":0.08,\"y\":0.78},{\"duration\":5,\"curve\":[0,0,0.5,1],\"x\":0.08,\"y\":0.78},{\"duration\":19,\"curve\":[0.5,0,1,1]},{\"duration\":14,\"x\":0.58}]},{\"name\":\"bbsR\",\"translateFrame\":[{\"duration\":4},{\"duration\":17,\"curve\":[0,0,0.5,1]},{\"duration\":29,\"x\":14.57,\"y\":33.69}],\"scaleFrame\":[{\"duration\":4},{\"duration\":17,\"curve\":[0,0,0.5,1]},{\"duration\":29,\"x\":1.39,\"y\":1.15}]},{\"name\":\"bb1\",\"translateFrame\":[{\"duration\":14},{\"duration\":9,\"curve\":[0,0,0.5,1],\"y\":150.14},{\"duration\":14,\"curve\":[0.5,0,1,1],\"y\":-231.65},{\"duration\":13,\"y\":-112.22}]},{\"name\":\"bb2\",\"translateFrame\":[{\"duration\":18},{\"duration\":9,\"curve\":[0,0,0.5,1],\"y\":150.14},{\"duration\":14,\"curve\":[0.5,0,1,1],\"y\":-231.65},{\"duration\":9,\"y\":-112.22}]},{\"name\":\"bbsL\",\"translateFrame\":[{\"duration\":4},{\"duration\":17,\"curve\":[0,0,0.5,1]},{\"duration\":29,\"x\":-15.48,\"y\":27.31}],\"scaleFrame\":[{\"duration\":4},{\"duration\":17,\"curve\":[0,0,0.5,1]},{\"duration\":29,\"x\":1.39,\"y\":1.15}]}],\"slot\":[{\"name\":\"sinkFaceU\",\"displayFrame\":[{\"duration\":4,\"value\":-1},{\"duration\":46}],\"colorFrame\":[{\"duration\":4},{\"duration\":4,\"tweenEasing\":0,\"value\":{\"aM\":0}},{\"duration\":4,\"tweenEasing\":0},{\"duration\":5,\"tweenEasing\":0},{\"duration\":33,\"value\":{\"aM\":0}}]},{\"name\":\"bottom_U\",\"displayFrame\":[{\"duration\":4},{\"duration\":46,\"value\":-1}]},{\"name\":\"sinkPoint\",\"displayFrame\":[{\"duration\":17},{\"duration\":33,\"value\":-1}],\"colorFrame\":[{\"duration\":12,\"tweenEasing\":0},{\"duration\":5,\"tweenEasing\":0},{\"duration\":33,\"value\":{\"aM\":0}}]},{\"name\":\"sinkPointSide\",\"displayFrame\":[{\"duration\":17},{\"duration\":33,\"value\":-1}],\"colorFrame\":[{\"duration\":12,\"tweenEasing\":0},{\"duration\":5,\"tweenEasing\":0},{\"duration\":33,\"value\":{\"aM\":0}}]},{\"name\":\"sbt\",\"displayFrame\":[{\"duration\":4,\"value\":-1},{\"duration\":46}],\"colorFrame\":[{\"duration\":4},{\"duration\":5,\"tweenEasing\":0,\"value\":{\"aM\":0}},{\"duration\":12,\"tweenEasing\":0},{\"duration\":7,\"tweenEasing\":0},{\"duration\":22,\"value\":{\"aM\":0}}]},{\"name\":\"smi\",\"displayFrame\":[{\"duration\":4,\"value\":-1},{\"duration\":46}],\"colorFrame\":[{\"duration\":30},{\"duration\":6,\"tweenEasing\":0},{\"duration\":14,\"value\":{\"aM\":0}}]},{\"name\":\"smo\",\"displayFrame\":[{\"duration\":14,\"value\":-1},{\"duration\":36}],\"colorFrame\":[{\"duration\":30},{\"duration\":6,\"tweenEasing\":0},{\"duration\":14,\"value\":{\"aM\":0}}]},{\"name\":\"smp\",\"displayFrame\":[{\"duration\":4,\"value\":-1},{\"duration\":46}],\"colorFrame\":[{\"duration\":24},{\"duration\":6,\"tweenEasing\":0},{\"duration\":20,\"value\":{\"aM\":0}}]},{\"name\":\"sbh\",\"displayFrame\":[{\"duration\":4,\"value\":-1},{\"duration\":46}],\"colorFrame\":[{\"duration\":4},{\"duration\":5,\"tweenEasing\":0,\"value\":{\"aM\":0}},{\"duration\":12,\"tweenEasing\":0},{\"duration\":7,\"tweenEasing\":0},{\"duration\":22,\"value\":{\"aM\":0}}]},{\"name\":\"bbsL\",\"displayFrame\":[{\"duration\":4,\"value\":-1},{\"duration\":46}],\"colorFrame\":[{\"duration\":4},{\"duration\":3,\"curve\":[0,0,0.5,1],\"value\":{\"aM\":0}},{\"duration\":8,\"tweenEasing\":0},{\"duration\":6,\"tweenEasing\":0},{\"duration\":29,\"value\":{\"aM\":0}}]},{\"name\":\"bbsR\",\"displayFrame\":[{\"duration\":4,\"value\":-1},{\"duration\":46}],\"colorFrame\":[{\"duration\":4},{\"duration\":3,\"curve\":[0,0,0.5,1],\"value\":{\"aM\":0}},{\"duration\":8,\"tweenEasing\":0},{\"duration\":6,\"tweenEasing\":0},{\"duration\":29,\"value\":{\"aM\":0}}]},{\"name\":\"bb1\",\"displayFrame\":[{\"duration\":14,\"value\":-1},{\"duration\":36}],\"colorFrame\":[{\"duration\":30},{\"duration\":7,\"tweenEasing\":0},{\"duration\":13,\"value\":{\"aM\":0}}]},{\"name\":\"bb2\",\"displayFrame\":[{\"duration\":18,\"value\":-1},{\"duration\":32}],\"colorFrame\":[{\"duration\":34},{\"duration\":7,\"tweenEasing\":0},{\"duration\":9,\"value\":{\"aM\":0}}]},{\"name\":\"sinkFaceU1\",\"displayFrame\":[{\"duration\":10},{\"duration\":40,\"value\":-1}],\"colorFrame\":[{\"duration\":4},{\"duration\":6,\"tweenEasing\":0},{\"duration\":40,\"value\":{\"aM\":0}}]}]},{\"duration\":10,\"playTimes\":0,\"name\":\"ActiveLoop\",\"bone\":[{\"name\":\"back\",\"translateFrame\":[{\"duration\":10,\"y\":-35.82}]},{\"name\":\"face\",\"translateFrame\":[{\"duration\":10,\"y\":-17.61}],\"scaleFrame\":[{\"duration\":10,\"x\":1.08,\"y\":0.61}]},{\"name\":\"bottom\",\"translateFrame\":[{\"duration\":10,\"x\":-1.62,\"y\":29.23}],\"scaleFrame\":[{\"duration\":10,\"x\":1.13,\"y\":0.67}]},{\"name\":\"sinkBottom\",\"scaleFrame\":[{\"duration\":10,\"x\":0.77,\"y\":0.77}]},{\"name\":\"sinkPoint\",\"translateFrame\":[{\"duration\":10,\"y\":-2.86}],\"scaleFrame\":[{\"duration\":5,\"tweenEasing\":0,\"x\":1.65,\"y\":0.73},{\"duration\":5,\"tweenEasing\":0,\"x\":1.51,\"y\":0.78},{\"duration\":0,\"x\":1.65,\"y\":0.73}]}],\"slot\":[{\"name\":\"bottom_U\",\"displayFrame\":[{\"duration\":10}]},{\"name\":\"sinkBottom\",\"colorFrame\":[{\"duration\":10,\"value\":{\"aM\":0}}]},{\"name\":\"sinkBottomSide\",\"colorFrame\":[{\"duration\":10,\"value\":{\"aM\":0}}]},{\"name\":\"sinkPoint\",\"displayFrame\":[{\"duration\":10}]},{\"name\":\"sinkPointSide\",\"displayFrame\":[{\"duration\":10}]},{\"name\":\"sinkFaceU1\",\"displayFrame\":[{\"duration\":10}]}]},{\"duration\":41,\"playTimes\":0,\"name\":\"Die\",\"frame\":[{\"duration\":4},{\"duration\":37,\"events\":[{\"name\":\"splash\"}]},{\"duration\":0,\"events\":[{\"name\":\"die\"}]}],\"bone\":[{\"name\":\"back\",\"translateFrame\":[{\"duration\":6,\"tweenEasing\":0},{\"duration\":35,\"y\":-20.21}],\"scaleFrame\":[{\"duration\":6,\"tweenEasing\":0},{\"duration\":35,\"x\":0.79,\"y\":0.79}]},{\"name\":\"splash\",\"translateFrame\":[{\"duration\":4},{\"duration\":37,\"y\":84.09}]},{\"name\":\"face\",\"scaleFrame\":[{\"duration\":6,\"tweenEasing\":0},{\"duration\":35,\"x\":0.67,\"y\":0.67}]},{\"name\":\"smi\",\"scaleFrame\":[{\"duration\":4},{\"duration\":13,\"curve\":[0,0,0.5,1],\"x\":0.08,\"y\":0.78},{\"duration\":5,\"curve\":[0,0,0.5,1],\"x\":0.08,\"y\":0.78},{\"duration\":14,\"curve\":[0.5,0,1,1]},{\"duration\":5,\"x\":0.58}]},{\"name\":\"sbt\",\"scaleFrame\":[{\"duration\":4},{\"duration\":11,\"curve\":[0,0,0.5,1],\"x\":0.7,\"y\":0.7},{\"duration\":13,\"curve\":[0.5,0,1,1],\"x\":1.73,\"y\":1.02},{\"duration\":13,\"x\":0.99,\"y\":1.51}]},{\"name\":\"sbh\",\"translateFrame\":[{\"duration\":4},{\"duration\":11,\"curve\":[0,0,0.5,1]},{\"duration\":13,\"curve\":[0.5,0,1,1],\"y\":25.45},{\"duration\":13,\"y\":-3.19}],\"scaleFrame\":[{\"duration\":4},{\"duration\":11,\"curve\":[0,0,0.5,1],\"x\":0.7,\"y\":0.7},{\"duration\":13,\"curve\":[0.5,0,1,1],\"y\":2.1},{\"duration\":13,\"x\":1.5,\"y\":0.91}]},{\"name\":\"bb2\",\"translateFrame\":[{\"duration\":18},{\"duration\":9,\"curve\":[0,0,0.5,1],\"y\":150.14},{\"duration\":14,\"curve\":[0.5,0,1,1],\"y\":-231.65},{\"duration\":0,\"y\":-112.22}]},{\"name\":\"smo\",\"scaleFrame\":[{\"duration\":4},{\"duration\":10,\"curve\":[0,0,0.5,1],\"x\":0.08,\"y\":0.78},{\"duration\":5,\"curve\":[0,0,0.5,1],\"x\":0.08,\"y\":0.78},{\"duration\":17,\"curve\":[0.5,0,1,1]},{\"duration\":5,\"x\":0.58}]},{\"name\":\"smp\",\"scaleFrame\":[{\"duration\":4},{\"duration\":8,\"curve\":[0,0,0.5,1],\"x\":0.08,\"y\":0.78},{\"duration\":5,\"curve\":[0,0,0.5,1],\"x\":0.08,\"y\":0.78},{\"duration\":19,\"curve\":[0.5,0,1,1]},{\"duration\":5,\"x\":0.58}]},{\"name\":\"bbsR\",\"translateFrame\":[{\"duration\":4},{\"duration\":17,\"curve\":[0,0,0.5,1]},{\"duration\":20,\"x\":14.57,\"y\":33.69}],\"scaleFrame\":[{\"duration\":4},{\"duration\":17,\"curve\":[0,0,0.5,1]},{\"duration\":20,\"x\":1.39,\"y\":1.15}]},{\"name\":\"bb1\",\"translateFrame\":[{\"duration\":14},{\"duration\":9,\"curve\":[0,0,0.5,1],\"y\":150.14},{\"duration\":14,\"curve\":[0.5,0,1,1],\"y\":-231.65},{\"duration\":4,\"y\":-112.22}]},{\"name\":\"bbsL\",\"translateFrame\":[{\"duration\":4},{\"duration\":17,\"curve\":[0,0,0.5,1]},{\"duration\":20,\"x\":-15.48,\"y\":27.31}],\"scaleFrame\":[{\"duration\":4},{\"duration\":17,\"curve\":[0,0,0.5,1]},{\"duration\":20,\"x\":1.39,\"y\":1.15}]}],\"slot\":[{\"name\":\"faceU\",\"colorFrame\":[{\"duration\":6,\"tweenEasing\":0},{\"duration\":35,\"value\":{\"aM\":0}}]},{\"name\":\"sinkBottom\",\"colorFrame\":[{\"duration\":6,\"tweenEasing\":0},{\"duration\":35,\"value\":{\"aM\":0}}]},{\"name\":\"sinkBottomSide\",\"colorFrame\":[{\"duration\":6,\"tweenEasing\":0},{\"duration\":35,\"value\":{\"aM\":0}}]},{\"name\":\"sbt\",\"displayFrame\":[{\"duration\":4,\"value\":-1},{\"duration\":37}],\"colorFrame\":[{\"duration\":4},{\"duration\":5,\"tweenEasing\":0,\"value\":{\"aM\":0}},{\"duration\":12,\"tweenEasing\":0},{\"duration\":7,\"tweenEasing\":0},{\"duration\":13,\"value\":{\"aM\":0}}]},{\"name\":\"smi\",\"displayFrame\":[{\"duration\":4,\"value\":-1},{\"duration\":37}],\"colorFrame\":[{\"duration\":30},{\"duration\":6,\"tweenEasing\":0},{\"duration\":5,\"value\":{\"aM\":0}}]},{\"name\":\"smo\",\"displayFrame\":[{\"duration\":14,\"value\":-1},{\"duration\":27}],\"colorFrame\":[{\"duration\":30},{\"duration\":6,\"tweenEasing\":0},{\"duration\":5,\"value\":{\"aM\":0}}]},{\"name\":\"smp\",\"displayFrame\":[{\"duration\":4,\"value\":-1},{\"duration\":37}],\"colorFrame\":[{\"duration\":24},{\"duration\":6,\"tweenEasing\":0},{\"duration\":11,\"value\":{\"aM\":0}}]},{\"name\":\"sbh\",\"displayFrame\":[{\"duration\":4,\"value\":-1},{\"duration\":37}],\"colorFrame\":[{\"duration\":4},{\"duration\":5,\"tweenEasing\":0,\"value\":{\"aM\":0}},{\"duration\":12,\"tweenEasing\":0},{\"duration\":7,\"tweenEasing\":0},{\"duration\":13,\"value\":{\"aM\":0}}]},{\"name\":\"bbsL\",\"displayFrame\":[{\"duration\":4,\"value\":-1},{\"duration\":37}],\"colorFrame\":[{\"duration\":4},{\"duration\":3,\"curve\":[0,0,0.5,1],\"value\":{\"aM\":0}},{\"duration\":8,\"tweenEasing\":0},{\"duration\":6,\"tweenEasing\":0},{\"duration\":20,\"value\":{\"aM\":0}}]},{\"name\":\"bbsR\",\"displayFrame\":[{\"duration\":4,\"value\":-1},{\"duration\":37}],\"colorFrame\":[{\"duration\":4},{\"duration\":3,\"curve\":[0,0,0.5,1],\"value\":{\"aM\":0}},{\"duration\":8,\"tweenEasing\":0},{\"duration\":6,\"tweenEasing\":0},{\"duration\":20,\"value\":{\"aM\":0}}]},{\"name\":\"bb1\",\"displayFrame\":[{\"duration\":14,\"value\":-1},{\"duration\":27}],\"colorFrame\":[{\"duration\":30},{\"duration\":7,\"tweenEasing\":0},{\"duration\":4,\"value\":{\"aM\":0}}]},{\"name\":\"bb2\",\"displayFrame\":[{\"duration\":18,\"value\":-1},{\"duration\":23}],\"colorFrame\":[{\"duration\":34},{\"duration\":7,\"tweenEasing\":0},{\"duration\":0,\"value\":{\"aM\":0}}]}]}],\"defaultActions\":[{\"gotoAndPlay\":\"Idle\"}]},{\"type\":\"Armature\",\"frameRate\":30,\"name\":\"_wvU_D\",\"aabb\":{\"x\":-79.63,\"y\":-86.4,\"width\":148.96,\"height\":174.92},\"bone\":[{\"name\":\"root\"},{\"name\":\"wv5\",\"parent\":\"root\",\"transform\":{\"x\":35.35,\"y\":-65.25}},{\"name\":\"wv2\",\"parent\":\"root\",\"transform\":{\"x\":-58.55,\"y\":-54.55}},{\"name\":\"wv0\",\"parent\":\"root\",\"transform\":{\"x\":58.8,\"y\":-22.85}},{\"name\":\"wv01\",\"parent\":\"root\",\"transform\":{\"x\":-31.1,\"y\":-76.8}},{\"name\":\"wv\",\"parent\":\"root\",\"transform\":{\"x\":-56.6368,\"y\":28.0638}},{\"name\":\"wv02\",\"parent\":\"root\",\"transform\":{\"x\":64,\"y\":21.05}},{\"name\":\"wv03\",\"parent\":\"root\",\"transform\":{\"x\":4.85,\"y\":78.65}}],\"slot\":[{\"name\":\"wv5\",\"parent\":\"wv5\"},{\"name\":\"wv2\",\"parent\":\"wv2\"},{\"name\":\"wv0\",\"parent\":\"wv0\"},{\"name\":\"wv01\",\"parent\":\"wv01\"},{\"name\":\"wv\",\"parent\":\"wv\"},{\"name\":\"wv02\",\"parent\":\"wv02\"},{\"name\":\"wv03\",\"parent\":\"wv03\"}],\"skin\":[{\"slot\":[{\"name\":\"wv01\",\"display\":[{\"name\":\"wv0\",\"transform\":{\"x\":0.92,\"y\":4.4,\"skX\":-81.69,\"skY\":-81.69}}]},{\"name\":\"wv0\",\"display\":[{\"name\":\"wv0\",\"transform\":{\"x\":-4.54,\"y\":1.35}}]},{\"name\":\"wv2\",\"display\":[{\"name\":\"wv2\",\"transform\":{\"x\":4.29,\"y\":3.5}}]},{\"name\":\"wv5\",\"display\":[{\"name\":\"wv5\",\"transform\":{\"x\":0.01,\"y\":0.17}}]},{\"name\":\"wv\",\"display\":[{\"name\":\"wv\",\"transform\":{\"x\":5.5,\"y\":-2.28,\"skX\":-43.77,\"skY\":-43.77,\"scX\":0.6209,\"scY\":0.6209}}]},{\"name\":\"wv02\",\"display\":[{\"name\":\"wv0\",\"transform\":{\"x\":-5.17,\"y\":0.74,\"skX\":23.64,\"skY\":23.64,\"scX\":1.2113,\"scY\":1.2113}}]},{\"name\":\"wv03\",\"display\":[{\"name\":\"wv0\",\"transform\":{\"x\":-1.19,\"y\":-4.13,\"skX\":112.08,\"skY\":112.08,\"scY\":1.4447}}]}]}],\"animation\":[{\"duration\":50,\"playTimes\":0,\"name\":\"idle\",\"bone\":[{\"name\":\"wv5\",\"translateFrame\":[{\"duration\":10},{\"duration\":30,\"curve\":[0.5,0,0.5,1]},{\"duration\":10,\"x\":0.61,\"y\":14.02}]},{\"name\":\"wv2\",\"translateFrame\":[{\"duration\":30,\"curve\":[0.5,0,0.5,1]},{\"duration\":20,\"x\":11.58,\"y\":10.06}]},{\"name\":\"wv0\",\"translateFrame\":[{\"duration\":5,\"curve\":[0,0,0.5,1],\"x\":-11.96,\"y\":2.92},{\"duration\":20,\"tweenEasing\":0,\"x\":-12.5,\"y\":3.05},{\"duration\":25,\"curve\":[0.5,0,1,1]},{\"duration\":0,\"x\":-11.96,\"y\":2.92}]},{\"name\":\"wv01\",\"translateFrame\":[{\"duration\":30,\"curve\":[0.5,0,0.5,1]},{\"duration\":20,\"x\":5.49,\"y\":16.76}]},{\"name\":\"wv\",\"translateFrame\":[{\"duration\":20},{\"duration\":30,\"curve\":[0.5,0,0.5,1]},{\"duration\":0,\"x\":12.7,\"y\":-5.87}]},{\"name\":\"wv02\",\"translateFrame\":[{\"duration\":15,\"curve\":[0,0,0.5,1],\"x\":-8.08,\"y\":0.76},{\"duration\":20,\"tweenEasing\":0,\"x\":-16.16,\"y\":1.52},{\"duration\":15,\"curve\":[0.5,0,1,1]},{\"duration\":0,\"x\":-8.08,\"y\":0.76}]},{\"name\":\"wv03\",\"translateFrame\":[{\"duration\":15},{\"duration\":30,\"curve\":[0.5,0,0.5,1]},{\"duration\":5,\"x\":0.91,\"y\":-18.9}]}],\"slot\":[{\"name\":\"wv5\",\"displayFrame\":[{\"duration\":10,\"value\":-1},{\"duration\":30},{\"duration\":10,\"value\":-1}],\"colorFrame\":[{\"duration\":10},{\"duration\":15,\"curve\":[0.5,0,0.5,1],\"value\":{\"aM\":0}},{\"duration\":15,\"curve\":[0.5,0,0.5,1]},{\"duration\":10,\"value\":{\"aM\":0}}]},{\"name\":\"wv2\",\"displayFrame\":[{\"duration\":30},{\"duration\":20,\"value\":-1}],\"colorFrame\":[{\"duration\":15,\"curve\":[0.5,0,0.5,1],\"value\":{\"aM\":0}},{\"duration\":15,\"curve\":[0.5,0,0.5,1]},{\"duration\":20,\"value\":{\"aM\":0}}]},{\"name\":\"wv0\",\"displayFrame\":[{\"duration\":5},{\"duration\":20,\"value\":-1},{\"duration\":25}],\"colorFrame\":[{\"duration\":5,\"curve\":[0,0,0.5,1],\"value\":{\"aM\":20}},{\"duration\":20,\"tweenEasing\":0,\"value\":{\"aM\":0}},{\"duration\":15,\"curve\":[0.5,0,0.5,1],\"value\":{\"aM\":0}},{\"duration\":10,\"curve\":[0.5,0,1,1]},{\"duration\":0,\"value\":{\"aM\":20}}]},{\"name\":\"wv01\",\"displayFrame\":[{\"duration\":30},{\"duration\":20,\"value\":-1}],\"colorFrame\":[{\"duration\":15,\"curve\":[0.5,0,0.5,1],\"value\":{\"aM\":0}},{\"duration\":15,\"curve\":[0.5,0,0.5,1]},{\"duration\":20,\"value\":{\"aM\":0}}]},{\"name\":\"wv\",\"displayFrame\":[{\"duration\":20,\"value\":-1},{\"duration\":30},{\"duration\":0,\"value\":-1}],\"colorFrame\":[{\"duration\":20},{\"duration\":15,\"curve\":[0.5,0,0.5,1],\"value\":{\"aM\":0}},{\"duration\":15,\"curve\":[0.5,0,0.5,1]},{\"duration\":0,\"value\":{\"aM\":0}}]},{\"name\":\"wv02\",\"displayFrame\":[{\"duration\":15},{\"duration\":20,\"value\":-1},{\"duration\":15}],\"colorFrame\":[{\"duration\":15,\"curve\":[0.5,0,0.5,1]},{\"duration\":20,\"tweenEasing\":0,\"value\":{\"aM\":0}},{\"duration\":15,\"curve\":[0.5,0,0.5,1],\"value\":{\"aM\":0}},{\"duration\":0}]},{\"name\":\"wv03\",\"displayFrame\":[{\"duration\":15,\"value\":-1},{\"duration\":35}],\"colorFrame\":[{\"duration\":15},{\"duration\":15,\"curve\":[0.5,0,0.5,1],\"value\":{\"aM\":0}},{\"duration\":15,\"curve\":[0.5,0,0.5,1]},{\"duration\":5,\"value\":{\"aM\":0}}]}]}],\"defaultActions\":[{\"gotoAndPlay\":\"idle\"}]},{\"type\":\"Armature\",\"frameRate\":30,\"name\":\"Down_U\",\"aabb\":{\"x\":-36.34,\"y\":-53.95,\"width\":72,\"height\":99},\"bone\":[{\"name\":\"root\"},{\"name\":\"main\",\"parent\":\"root\",\"transform\":{\"y\":4.7517,\"scX\":1.15,\"scY\":1.15}},{\"length\":49,\"name\":\"back\",\"parent\":\"main\",\"transform\":{\"y\":-9.0716}},{\"name\":\"splash\",\"parent\":\"main\",\"transform\":{\"y\":-38.5676,\"scX\":0.3552,\"scY\":0.3552}},{\"length\":54,\"name\":\"sinkPoint\",\"parent\":\"main\",\"transform\":{\"x\":1.759,\"y\":47.101,\"scX\":0.571,\"scY\":0.9892}},{\"name\":\"face\",\"parent\":\"main\",\"transform\":{\"x\":-0.2921,\"y\":-8.0035}},{\"length\":407,\"name\":\"smi\",\"parent\":\"splash\",\"transform\":{\"y\":-1.45,\"skX\":-90,\"skY\":-90,\"scX\":0.7369,\"scY\":0.4691}},{\"length\":129,\"name\":\"sbt\",\"parent\":\"splash\",\"transform\":{\"y\":-8.15,\"skX\":-90.3545,\"skY\":-90.3545,\"scX\":0.5846,\"scY\":0.7667}},{\"name\":\"sbh\",\"parent\":\"splash\",\"transform\":{\"scX\":0.7644,\"scY\":0.7644}},{\"name\":\"bb2\",\"parent\":\"splash\",\"transform\":{\"x\":24.8261,\"y\":-168.3}},{\"length\":302,\"name\":\"smo\",\"parent\":\"splash\",\"transform\":{\"skX\":-90,\"skY\":-90,\"scX\":0.7577,\"scY\":0.7577}},{\"length\":353,\"name\":\"smp\",\"parent\":\"splash\",\"transform\":{\"skX\":-90,\"skY\":-90,\"scX\":0.7416,\"scY\":0.7416}},{\"name\":\"bbsR\",\"parent\":\"splash\",\"transform\":{\"x\":94.35,\"y\":3.25}},{\"name\":\"bb1\",\"parent\":\"splash\",\"transform\":{\"x\":-75.8,\"y\":-148.6}},{\"name\":\"bbsL\",\"parent\":\"splash\",\"transform\":{\"x\":-57.7577,\"y\":9.7211}}],\"slot\":[{\"displayIndex\":-1,\"name\":\"sinkFaceU1\",\"parent\":\"root\"},{\"name\":\"_wvD\",\"parent\":\"main\"},{\"displayIndex\":-1,\"name\":\"backU\",\"parent\":\"back\"},{\"name\":\"faceU\",\"parent\":\"face\"},{\"displayIndex\":-1,\"name\":\"sinkPoint\",\"parent\":\"sinkPoint\"},{\"displayIndex\":-1,\"name\":\"sinkPointSide\",\"parent\":\"sinkPoint\"},{\"displayIndex\":-1,\"name\":\"sbt\",\"parent\":\"sbt\"},{\"displayIndex\":-1,\"name\":\"smi\",\"parent\":\"smi\"},{\"displayIndex\":-1,\"name\":\"smo\",\"parent\":\"smo\"},{\"displayIndex\":-1,\"name\":\"smp\",\"parent\":\"smp\"},{\"displayIndex\":-1,\"name\":\"sbh\",\"parent\":\"sbh\"},{\"displayIndex\":-1,\"name\":\"bbsL\",\"parent\":\"bbsL\"},{\"displayIndex\":-1,\"name\":\"bbsR\",\"parent\":\"bbsR\"},{\"displayIndex\":-1,\"name\":\"bb1\",\"parent\":\"bb1\"},{\"displayIndex\":-1,\"name\":\"bb2\",\"parent\":\"bb2\"}],\"skin\":[{\"slot\":[{\"name\":\"smo\",\"display\":[{\"name\":\"s\",\"transform\":{\"x\":116.88,\"y\":-1.58,\"skX\":90,\"skY\":90},\"path\":\"tide/splashMainOuter\"}]},{\"name\":\"_wvD\",\"display\":[{\"type\":\"armature\",\"name\":\"_wvD\",\"transform\":{\"scX\":0.7617,\"scY\":0.7617},\"path\":\"_wvD_U\"}]},{\"name\":\"sbh\",\"display\":[{\"name\":\"s\",\"transform\":{\"x\":5.86,\"y\":-52.3},\"path\":\"tide/splash_baseHere\"}]},{\"name\":\"faceU\",\"display\":[{\"name\":\"faceU\",\"path\":\"faceD\"}]},{\"name\":\"bbsR\",\"display\":[{\"name\":\"s\",\"transform\":{\"x\":5.67,\"y\":-5.27},\"path\":\"tide/splash_bubblesR\"}]},{\"name\":\"sinkPointSide\",\"display\":[{\"name\":\"sinkBottomSide\",\"transform\":{\"x\":0.86,\"y\":-2.45}}]},{\"name\":\"bb2\",\"display\":[{\"name\":\"s\",\"transform\":{\"x\":-3.08,\"y\":3.74},\"path\":\"tide/splash_bubble2\"}]},{\"name\":\"smi\",\"display\":[{\"name\":\"s\",\"transform\":{\"x\":188.71,\"y\":-5.69,\"skX\":90,\"skY\":90},\"path\":\"tide/splashMainInner\"}]},{\"name\":\"sinkFaceU1\",\"display\":[{\"name\":\"sinkFaceU\",\"transform\":{\"x\":-0.64,\"y\":11.11,\"scX\":1.5089,\"scY\":1.2465}}]},{\"name\":\"smp\",\"display\":[{\"name\":\"s\",\"transform\":{\"x\":179.83,\"y\":0.76,\"skX\":90,\"skY\":90},\"path\":\"tide/splashMainPush\"}]},{\"name\":\"backU\",\"display\":[{\"name\":\"backU\",\"transform\":{\"skX\":180,\"skY\":180},\"path\":\"bottom_U\"}]},{\"name\":\"bbsL\",\"display\":[{\"name\":\"s\",\"transform\":{\"x\":-30.06,\"y\":-8.51},\"path\":\"tide/splash_bubblesL\"}]},{\"name\":\"sinkPoint\",\"display\":[{\"name\":\"sinkBottom\",\"transform\":{\"x\":0.18,\"y\":3.28}}]},{\"name\":\"bb1\",\"display\":[{\"name\":\"s\",\"transform\":{\"x\":2.99,\"y\":3.8},\"path\":\"tide/splash_bubble1\"}]},{\"name\":\"sbt\",\"display\":[{\"name\":\"s\",\"transform\":{\"x\":123.94,\"y\":8.1,\"skX\":90.35,\"skY\":90.35},\"path\":\"tide/splash_baseThere\"}]}]}],\"animation\":[{\"duration\":100,\"playTimes\":0,\"name\":\"Idle\",\"bone\":[{\"name\":\"face\",\"translateFrame\":[{\"duration\":25,\"curve\":[0,0,0.5,1]},{\"duration\":25,\"curve\":[0.5,0,1,1],\"x\":-2.31,\"y\":-3.15},{\"duration\":25,\"curve\":[0,0,0.5,1]},{\"duration\":25,\"curve\":[0.5,0,1,1],\"x\":1.15,\"y\":3.81},{\"duration\":0}],\"rotateFrame\":[{\"duration\":25,\"curve\":[0,0,0.5,1]},{\"duration\":25,\"curve\":[0.5,0,1,1],\"rotate\":-1.29},{\"duration\":50}],\"scaleFrame\":[{\"duration\":25,\"curve\":[0,0,0.5,1]},{\"duration\":25,\"curve\":[0.5,0,1,1],\"x\":1.01,\"y\":0.97},{\"duration\":25,\"curve\":[0,0,0.5,1]},{\"duration\":25,\"curve\":[0.5,0,1,1],\"x\":0.98,\"y\":1.04},{\"duration\":0}]},{\"name\":\"sinkPoint\",\"scaleFrame\":[{\"duration\":25,\"curve\":[0,0,0.5,1]},{\"duration\":25,\"curve\":[0.5,0,1,1],\"x\":0.99,\"y\":1.1},{\"duration\":25,\"curve\":[0,0,0.5,1]},{\"duration\":25,\"curve\":[0.5,0,1,1],\"x\":0.97,\"y\":1.04},{\"duration\":0}]}]},{\"duration\":37,\"playTimes\":0,\"name\":\"ActiveStart\",\"frame\":[{},{\"events\":[{\"name\":\"splash\"}]},{\"duration\":0,\"events\":[{\"name\":\"move\"}]}],\"bone\":[{\"name\":\"back\",\"translateFrame\":[{\"duration\":6,\"curve\":[0,0,0.5,1]},{\"duration\":7,\"curve\":[0.5,0,0.5,1],\"x\":-1.3,\"y\":-9.87},{\"duration\":24,\"x\":-1.86,\"y\":2.58}],\"scaleFrame\":[{\"duration\":6,\"curve\":[0,0,0.5,1]},{\"duration\":7,\"curve\":[0.5,0,0.5,1],\"x\":1.21},{\"duration\":24,\"x\":1.2,\"y\":1.09}]},{\"name\":\"face\",\"translateFrame\":[{\"duration\":6,\"curve\":[0,0,0.5,1]},{\"duration\":7,\"curve\":[0.5,0,0.5,1],\"y\":1.97},{\"duration\":24,\"y\":13.53}],\"scaleFrame\":[{\"duration\":6,\"curve\":[0,0,0.5,1]},{\"duration\":7,\"curve\":[0.5,0,0.5,1],\"x\":1.22,\"y\":1.09},{\"duration\":24,\"x\":1.22,\"y\":1.16}]},{\"name\":\"sinkPoint\",\"translateFrame\":[{\"duration\":4,\"tweenEasing\":0,\"y\":-16.7},{\"duration\":33,\"y\":-6.34}],\"scaleFrame\":[{\"duration\":4,\"tweenEasing\":0},{\"duration\":33,\"x\":1.34,\"y\":0.92}]},{\"name\":\"splash\",\"translateFrame\":[{\"duration\":37,\"y\":92.61}]},{\"name\":\"sbt\",\"scaleFrame\":[{\"duration\":11,\"curve\":[0,0,0.5,1],\"x\":0.7,\"y\":0.7},{\"duration\":13,\"curve\":[0.5,0,1,1],\"x\":1.73,\"y\":1.02},{\"duration\":13,\"x\":0.99,\"y\":1.51}]},{\"name\":\"sbh\",\"translateFrame\":[{\"duration\":11,\"curve\":[0,0,0.5,1]},{\"duration\":13,\"curve\":[0.5,0,1,1],\"y\":25.45},{\"duration\":13,\"y\":-3.19}],\"scaleFrame\":[{\"duration\":11,\"curve\":[0,0,0.5,1],\"x\":0.7,\"y\":0.7},{\"duration\":13,\"curve\":[0.5,0,1,1],\"y\":2.1},{\"duration\":13,\"x\":1.5,\"y\":0.91}]},{\"name\":\"smi\",\"scaleFrame\":[{\"duration\":13,\"curve\":[0,0,0.5,1],\"x\":0.08,\"y\":0.78},{\"duration\":5,\"curve\":[0,0,0.5,1],\"x\":0.08,\"y\":0.78},{\"duration\":14,\"curve\":[0.5,0,1,1]},{\"duration\":5,\"x\":0.58}]},{\"name\":\"smo\",\"scaleFrame\":[{\"duration\":10,\"curve\":[0,0,0.5,1],\"x\":0.08,\"y\":0.78},{\"duration\":5,\"curve\":[0,0,0.5,1],\"x\":0.08,\"y\":0.78},{\"duration\":17,\"curve\":[0.5,0,1,1]},{\"duration\":5,\"x\":0.58}]},{\"name\":\"smp\",\"scaleFrame\":[{\"duration\":8,\"curve\":[0,0,0.5,1],\"x\":0.08,\"y\":0.78},{\"duration\":5,\"curve\":[0,0,0.5,1],\"x\":0.08,\"y\":0.78},{\"duration\":19,\"curve\":[0.5,0,1,1]},{\"duration\":5,\"x\":0.58}]},{\"name\":\"bbsR\",\"translateFrame\":[{\"duration\":17,\"curve\":[0,0,0.5,1]},{\"duration\":20,\"x\":14.57,\"y\":33.69}],\"scaleFrame\":[{\"duration\":17,\"curve\":[0,0,0.5,1]},{\"duration\":20,\"x\":1.39,\"y\":1.15}]},{\"name\":\"bb1\",\"translateFrame\":[{\"duration\":10},{\"duration\":9,\"curve\":[0,0,0.5,1],\"y\":150.14},{\"duration\":14,\"curve\":[0.5,0,1,1],\"y\":-231.65},{\"duration\":4,\"y\":-112.22}]},{\"name\":\"bb2\",\"translateFrame\":[{\"duration\":14},{\"duration\":9,\"curve\":[0,0,0.5,1],\"y\":150.14},{\"duration\":14,\"curve\":[0.5,0,1,1],\"y\":-231.65},{\"duration\":0,\"y\":-112.22}]},{\"name\":\"bbsL\",\"translateFrame\":[{\"duration\":17,\"curve\":[0,0,0.5,1]},{\"duration\":20,\"x\":-15.48,\"y\":27.31}],\"scaleFrame\":[{\"duration\":17,\"curve\":[0,0,0.5,1]},{\"duration\":20,\"x\":1.39,\"y\":1.15}]}],\"slot\":[{\"name\":\"sinkPoint\",\"displayFrame\":[{\"duration\":37}]},{\"name\":\"sinkPointSide\",\"displayFrame\":[{\"duration\":37}],\"colorFrame\":[{\"duration\":4,\"tweenEasing\":0,\"value\":{\"aM\":0}},{\"duration\":33}]},{\"name\":\"sbt\",\"displayFrame\":[{\"duration\":37}],\"colorFrame\":[{\"duration\":5,\"tweenEasing\":0,\"value\":{\"aM\":0}},{\"duration\":12,\"tweenEasing\":0},{\"duration\":7,\"tweenEasing\":0},{\"duration\":13,\"value\":{\"aM\":0}}]},{\"name\":\"smi\",\"displayFrame\":[{\"duration\":37}],\"colorFrame\":[{\"duration\":26},{\"duration\":6,\"tweenEasing\":0},{\"duration\":5,\"value\":{\"aM\":0}}]},{\"name\":\"smo\",\"displayFrame\":[{\"duration\":10,\"value\":-1},{\"duration\":27}],\"colorFrame\":[{\"duration\":26},{\"duration\":6,\"tweenEasing\":0},{\"duration\":5,\"value\":{\"aM\":0}}]},{\"name\":\"smp\",\"displayFrame\":[{\"duration\":37}],\"colorFrame\":[{\"duration\":20},{\"duration\":6,\"tweenEasing\":0},{\"duration\":11,\"value\":{\"aM\":0}}]},{\"name\":\"sbh\",\"displayFrame\":[{\"duration\":37}],\"colorFrame\":[{\"duration\":5,\"tweenEasing\":0,\"value\":{\"aM\":0}},{\"duration\":12,\"tweenEasing\":0},{\"duration\":7,\"tweenEasing\":0},{\"duration\":13,\"value\":{\"aM\":0}}]},{\"name\":\"bbsL\",\"displayFrame\":[{\"duration\":37}],\"colorFrame\":[{\"duration\":3,\"curve\":[0,0,0.5,1],\"value\":{\"aM\":0}},{\"duration\":8,\"tweenEasing\":0},{\"duration\":6,\"tweenEasing\":0},{\"duration\":20,\"value\":{\"aM\":0}}]},{\"name\":\"bbsR\",\"displayFrame\":[{\"duration\":37}],\"colorFrame\":[{\"duration\":3,\"curve\":[0,0,0.5,1],\"value\":{\"aM\":0}},{\"duration\":8,\"tweenEasing\":0},{\"duration\":6,\"tweenEasing\":0},{\"duration\":20,\"value\":{\"aM\":0}}]},{\"name\":\"bb1\",\"displayFrame\":[{\"duration\":10,\"value\":-1},{\"duration\":27}],\"colorFrame\":[{\"duration\":26},{\"duration\":7,\"tweenEasing\":0},{\"duration\":4,\"value\":{\"aM\":0}}]},{\"name\":\"bb2\",\"displayFrame\":[{\"duration\":14,\"value\":-1},{\"duration\":23}],\"colorFrame\":[{\"duration\":30},{\"duration\":7,\"tweenEasing\":0},{\"duration\":0,\"value\":{\"aM\":0}}]},{\"name\":\"backU\",\"displayFrame\":[{\"duration\":37}]},{\"name\":\"sinkFaceU1\",\"displayFrame\":[{\"duration\":37}],\"colorFrame\":[{\"duration\":5,\"tweenEasing\":0,\"value\":{\"aM\":0}},{\"duration\":32}]}]},{\"duration\":50,\"playTimes\":0,\"name\":\"ActiveEnd\",\"frame\":[{\"duration\":4},{\"duration\":0,\"events\":[{\"name\":\"splash\"}]}],\"bone\":[{\"name\":\"back\",\"translateFrame\":[{\"duration\":4,\"tweenEasing\":0,\"x\":-1.86,\"y\":2.58},{\"duration\":46}],\"scaleFrame\":[{\"duration\":4,\"curve\":[0,0,0.5,1],\"x\":1.2,\"y\":1.09},{\"duration\":46}]},{\"name\":\"face\",\"translateFrame\":[{\"duration\":4,\"curve\":[0.5,0,0.5,1],\"y\":13.53},{\"duration\":13,\"curve\":[0,0,0.5,1]},{\"duration\":8,\"curve\":[0.5,0,1,1],\"y\":-10.62},{\"duration\":6,\"curve\":[0,0,0.5,1],\"x\":3.41,\"y\":6.45},{\"duration\":19,\"curve\":[0.5,0,0.5,1],\"x\":-0.76,\"y\":-6.07},{\"duration\":0}],\"scaleFrame\":[{\"duration\":4,\"curve\":[0.5,0,0.5,1],\"x\":1.22,\"y\":1.16},{\"duration\":8,\"curve\":[0,0,0.5,1]},{\"duration\":5,\"curve\":[0.5,0,0.5,1],\"x\":0.83,\"y\":0.83},{\"duration\":8,\"curve\":[0.5,0,1,1],\"x\":1.14,\"y\":1.23},{\"duration\":6,\"curve\":[0,0,0.5,1]},{\"duration\":19,\"curve\":[0.5,0,0.5,1],\"y\":0.93},{\"duration\":0}]},{\"name\":\"sinkPoint\",\"translateFrame\":[{\"duration\":4,\"tweenEasing\":0,\"y\":-6.34},{\"duration\":8,\"tweenEasing\":0,\"y\":-26.78},{\"duration\":5,\"curve\":[0.5,0,0.5,1],\"y\":-21.86},{\"duration\":14,\"tweenEasing\":0,\"y\":-9.84},{\"duration\":19,\"y\":-4.91}],\"scaleFrame\":[{\"duration\":4,\"tweenEasing\":0,\"x\":1.34,\"y\":0.92},{\"duration\":8,\"tweenEasing\":0,\"x\":1.34,\"y\":0.92},{\"duration\":5,\"curve\":[0.5,0,0.5,1],\"y\":1.08},{\"duration\":14,\"tweenEasing\":0,\"x\":0.62,\"y\":0.62},{\"duration\":19,\"curve\":[0.5,0,0.5,1],\"x\":0.62,\"y\":0.62},{\"duration\":0}]},{\"name\":\"splash\",\"translateFrame\":[{\"duration\":4},{\"duration\":46,\"y\":84.09}]},{\"name\":\"sbt\",\"scaleFrame\":[{\"duration\":4},{\"duration\":11,\"curve\":[0,0,0.5,1],\"x\":0.7,\"y\":0.7},{\"duration\":13,\"curve\":[0.5,0,1,1],\"x\":1.73,\"y\":1.02},{\"duration\":22,\"x\":0.99,\"y\":1.51}]},{\"name\":\"sbh\",\"translateFrame\":[{\"duration\":4},{\"duration\":11,\"curve\":[0,0,0.5,1]},{\"duration\":13,\"curve\":[0.5,0,1,1],\"y\":25.45},{\"duration\":22,\"y\":-3.19}],\"scaleFrame\":[{\"duration\":4},{\"duration\":11,\"curve\":[0,0,0.5,1],\"x\":0.7,\"y\":0.7},{\"duration\":13,\"curve\":[0.5,0,1,1],\"y\":2.1},{\"duration\":22,\"x\":1.5,\"y\":0.91}]},{\"name\":\"smi\",\"scaleFrame\":[{\"duration\":17,\"curve\":[0,0,0.5,1],\"x\":0.08,\"y\":0.78},{\"duration\":5,\"curve\":[0,0,0.5,1],\"x\":0.08,\"y\":0.78},{\"duration\":14,\"curve\":[0.5,0,1,1]},{\"duration\":14,\"x\":0.58}]},{\"name\":\"smo\",\"scaleFrame\":[{\"duration\":4},{\"duration\":10,\"curve\":[0,0,0.5,1],\"x\":0.08,\"y\":0.78},{\"duration\":5,\"curve\":[0,0,0.5,1],\"x\":0.08,\"y\":0.78},{\"duration\":17,\"curve\":[0.5,0,1,1]},{\"duration\":14,\"x\":0.58}]},{\"name\":\"smp\",\"scaleFrame\":[{\"duration\":4,\"curve\":[0.5,0,1,1]},{\"duration\":8,\"curve\":[0,0,0.5,1],\"x\":0.08,\"y\":0.78},{\"duration\":5,\"curve\":[0,0,0.5,1],\"x\":0.08,\"y\":0.78},{\"duration\":19,\"curve\":[0.5,0,1,1]},{\"duration\":14,\"x\":0.58}]},{\"name\":\"bbsR\",\"translateFrame\":[{\"duration\":4},{\"duration\":17,\"curve\":[0,0,0.5,1]},{\"duration\":29,\"x\":14.57,\"y\":33.69}],\"scaleFrame\":[{\"duration\":4},{\"duration\":17,\"curve\":[0,0,0.5,1]},{\"duration\":29,\"x\":1.39,\"y\":1.15}]},{\"name\":\"bb1\",\"translateFrame\":[{\"duration\":14},{\"duration\":9,\"curve\":[0,0,0.5,1],\"y\":150.14},{\"duration\":14,\"curve\":[0.5,0,1,1],\"y\":-231.65},{\"duration\":13,\"y\":-112.22}]},{\"name\":\"bb2\",\"translateFrame\":[{\"duration\":18},{\"duration\":9,\"curve\":[0,0,0.5,1],\"y\":150.14},{\"duration\":14,\"curve\":[0.5,0,1,1],\"y\":-231.65},{\"duration\":9,\"y\":-112.22}]},{\"name\":\"bbsL\",\"translateFrame\":[{\"duration\":4},{\"duration\":17,\"curve\":[0,0,0.5,1]},{\"duration\":29,\"x\":-15.48,\"y\":27.31}],\"scaleFrame\":[{\"duration\":4},{\"duration\":17,\"curve\":[0,0,0.5,1]},{\"duration\":29,\"x\":1.39,\"y\":1.15}]}],\"slot\":[{\"name\":\"faceU\",\"colorFrame\":[{\"duration\":4},{\"duration\":8,\"tweenEasing\":0},{\"duration\":3,\"tweenEasing\":0,\"value\":{\"aM\":63}},{\"duration\":35}]},{\"name\":\"sinkPoint\",\"displayFrame\":[{\"duration\":17},{\"duration\":33,\"value\":-1}],\"colorFrame\":[{\"duration\":12,\"tweenEasing\":0},{\"duration\":5,\"tweenEasing\":0},{\"duration\":33,\"value\":{\"aM\":0}}]},{\"name\":\"sinkPointSide\",\"displayFrame\":[{\"duration\":17},{\"duration\":33,\"value\":-1}],\"colorFrame\":[{\"duration\":12,\"tweenEasing\":0},{\"duration\":5,\"tweenEasing\":0},{\"duration\":33,\"value\":{\"aM\":0}}]},{\"name\":\"sbt\",\"displayFrame\":[{\"duration\":4,\"value\":-1},{\"duration\":46}],\"colorFrame\":[{\"duration\":4},{\"duration\":5,\"tweenEasing\":0,\"value\":{\"aM\":0}},{\"duration\":12,\"tweenEasing\":0},{\"duration\":7,\"tweenEasing\":0},{\"duration\":22,\"value\":{\"aM\":0}}]},{\"name\":\"smi\",\"displayFrame\":[{\"duration\":4,\"value\":-1},{\"duration\":46}],\"colorFrame\":[{\"duration\":30},{\"duration\":6,\"tweenEasing\":0},{\"duration\":14,\"value\":{\"aM\":0}}]},{\"name\":\"smo\",\"displayFrame\":[{\"duration\":14,\"value\":-1},{\"duration\":36}],\"colorFrame\":[{\"duration\":30},{\"duration\":6,\"tweenEasing\":0},{\"duration\":14,\"value\":{\"aM\":0}}]},{\"name\":\"smp\",\"displayFrame\":[{\"duration\":4,\"value\":-1},{\"duration\":46}],\"colorFrame\":[{\"duration\":24},{\"duration\":6,\"tweenEasing\":0},{\"duration\":20,\"value\":{\"aM\":0}}]},{\"name\":\"sbh\",\"displayFrame\":[{\"duration\":4,\"value\":-1},{\"duration\":46}],\"colorFrame\":[{\"duration\":4},{\"duration\":5,\"tweenEasing\":0,\"value\":{\"aM\":0}},{\"duration\":12,\"tweenEasing\":0},{\"duration\":7,\"tweenEasing\":0},{\"duration\":22,\"value\":{\"aM\":0}}]},{\"name\":\"bbsL\",\"displayFrame\":[{\"duration\":4,\"value\":-1},{\"duration\":46}],\"colorFrame\":[{\"duration\":4},{\"duration\":3,\"curve\":[0,0,0.5,1],\"value\":{\"aM\":0}},{\"duration\":8,\"tweenEasing\":0},{\"duration\":6,\"tweenEasing\":0},{\"duration\":29,\"value\":{\"aM\":0}}]},{\"name\":\"bbsR\",\"displayFrame\":[{\"duration\":4,\"value\":-1},{\"duration\":46}],\"colorFrame\":[{\"duration\":4},{\"duration\":3,\"curve\":[0,0,0.5,1],\"value\":{\"aM\":0}},{\"duration\":8,\"tweenEasing\":0},{\"duration\":6,\"tweenEasing\":0},{\"duration\":29,\"value\":{\"aM\":0}}]},{\"name\":\"bb1\",\"displayFrame\":[{\"duration\":14,\"value\":-1},{\"duration\":36}],\"colorFrame\":[{\"duration\":30},{\"duration\":7,\"tweenEasing\":0},{\"duration\":13,\"value\":{\"aM\":0}}]},{\"name\":\"bb2\",\"displayFrame\":[{\"duration\":18,\"value\":-1},{\"duration\":32}],\"colorFrame\":[{\"duration\":34},{\"duration\":7,\"tweenEasing\":0},{\"duration\":9,\"value\":{\"aM\":0}}]},{\"name\":\"backU\",\"displayFrame\":[{\"duration\":4},{\"duration\":46,\"value\":-1}]},{\"name\":\"sinkFaceU1\",\"displayFrame\":[{\"duration\":10},{\"duration\":40,\"value\":-1}],\"colorFrame\":[{\"duration\":4},{\"duration\":6,\"tweenEasing\":0},{\"duration\":40,\"value\":{\"aM\":0}}]}]},{\"duration\":10,\"playTimes\":0,\"name\":\"ActiveLoop\",\"bone\":[{\"name\":\"back\",\"translateFrame\":[{\"duration\":10,\"x\":-1.86,\"y\":2.58}],\"scaleFrame\":[{\"duration\":10,\"x\":1.2,\"y\":1.09}]},{\"name\":\"face\",\"translateFrame\":[{\"duration\":10,\"y\":13.53}],\"scaleFrame\":[{\"duration\":10,\"x\":1.22,\"y\":1.16}]},{\"name\":\"sinkPoint\",\"translateFrame\":[{\"duration\":10,\"y\":-6.34}],\"scaleFrame\":[{\"duration\":5,\"tweenEasing\":0,\"x\":1.34,\"y\":0.92},{\"duration\":5,\"tweenEasing\":0,\"x\":1.5,\"y\":0.85},{\"duration\":0,\"x\":1.34,\"y\":0.92}]},{\"name\":\"smi\",\"scaleFrame\":[{\"duration\":10,\"x\":0.08,\"y\":0.78}]}],\"slot\":[{\"name\":\"sinkPoint\",\"displayFrame\":[{\"duration\":10}]},{\"name\":\"sinkPointSide\",\"displayFrame\":[{\"duration\":10}]},{\"name\":\"backU\",\"displayFrame\":[{\"duration\":10}]},{\"name\":\"sinkFaceU1\",\"displayFrame\":[{\"duration\":10}]}]},{\"duration\":41,\"playTimes\":0,\"name\":\"Die\",\"frame\":[{\"duration\":4},{\"duration\":37,\"events\":[{\"name\":\"splash\"}]},{\"duration\":0,\"events\":[{\"name\":\"die\"}]}],\"bone\":[{\"name\":\"back\",\"translateFrame\":[{\"duration\":6,\"tweenEasing\":0},{\"duration\":35,\"y\":-19.13}],\"scaleFrame\":[{\"duration\":6,\"tweenEasing\":0},{\"duration\":35,\"x\":0.74,\"y\":0.74}]},{\"name\":\"splash\",\"translateFrame\":[{\"duration\":4},{\"duration\":37,\"y\":48.83}]},{\"name\":\"face\",\"scaleFrame\":[{\"duration\":6,\"tweenEasing\":0},{\"duration\":35,\"x\":0.74,\"y\":0.74}]},{\"name\":\"smi\",\"scaleFrame\":[{\"duration\":4},{\"duration\":13,\"curve\":[0,0,0.5,1],\"x\":0.08,\"y\":0.78},{\"duration\":5,\"curve\":[0,0,0.5,1],\"x\":0.08,\"y\":0.78},{\"duration\":14,\"curve\":[0.5,0,1,1]},{\"duration\":5,\"x\":0.58}]},{\"name\":\"sbt\",\"scaleFrame\":[{\"duration\":4},{\"duration\":11,\"curve\":[0,0,0.5,1],\"x\":0.7,\"y\":0.7},{\"duration\":13,\"curve\":[0.5,0,1,1],\"x\":1.73,\"y\":1.02},{\"duration\":13,\"x\":0.99,\"y\":1.51}]},{\"name\":\"sbh\",\"translateFrame\":[{\"duration\":4},{\"duration\":11,\"curve\":[0,0,0.5,1]},{\"duration\":13,\"curve\":[0.5,0,1,1],\"y\":25.45},{\"duration\":13,\"y\":-3.19}],\"scaleFrame\":[{\"duration\":4},{\"duration\":11,\"curve\":[0,0,0.5,1],\"x\":0.7,\"y\":0.7},{\"duration\":13,\"curve\":[0.5,0,1,1],\"y\":2.1},{\"duration\":13,\"x\":1.5,\"y\":0.91}]},{\"name\":\"bb2\",\"translateFrame\":[{\"duration\":18},{\"duration\":9,\"curve\":[0,0,0.5,1],\"y\":150.14},{\"duration\":14,\"curve\":[0.5,0,1,1],\"y\":-231.65},{\"duration\":0,\"y\":-112.22}]},{\"name\":\"smo\",\"scaleFrame\":[{\"duration\":4},{\"duration\":10,\"curve\":[0,0,0.5,1],\"x\":0.08,\"y\":0.78},{\"duration\":5,\"curve\":[0,0,0.5,1],\"x\":0.08,\"y\":0.78},{\"duration\":17,\"curve\":[0.5,0,1,1]},{\"duration\":5,\"x\":0.58}]},{\"name\":\"smp\",\"scaleFrame\":[{\"duration\":4},{\"duration\":8,\"curve\":[0,0,0.5,1],\"x\":0.08,\"y\":0.78},{\"duration\":5,\"curve\":[0,0,0.5,1],\"x\":0.08,\"y\":0.78},{\"duration\":19,\"curve\":[0.5,0,1,1]},{\"duration\":5,\"x\":0.58}]},{\"name\":\"bbsR\",\"translateFrame\":[{\"duration\":4},{\"duration\":17,\"curve\":[0,0,0.5,1]},{\"duration\":20,\"x\":14.57,\"y\":33.69}],\"scaleFrame\":[{\"duration\":4},{\"duration\":17,\"curve\":[0,0,0.5,1]},{\"duration\":20,\"x\":1.39,\"y\":1.15}]},{\"name\":\"bb1\",\"translateFrame\":[{\"duration\":14},{\"duration\":9,\"curve\":[0,0,0.5,1],\"y\":150.14},{\"duration\":14,\"curve\":[0.5,0,1,1],\"y\":-231.65},{\"duration\":4,\"y\":-112.22}]},{\"name\":\"bbsL\",\"translateFrame\":[{\"duration\":4},{\"duration\":17,\"curve\":[0,0,0.5,1]},{\"duration\":20,\"x\":-15.48,\"y\":27.31}],\"scaleFrame\":[{\"duration\":4},{\"duration\":17,\"curve\":[0,0,0.5,1]},{\"duration\":20,\"x\":1.39,\"y\":1.15}]}],\"slot\":[{\"name\":\"_wvD\",\"colorFrame\":[{\"duration\":26},{\"duration\":15,\"tweenEasing\":0},{\"duration\":0,\"value\":{\"aM\":0}}]},{\"name\":\"faceU\",\"colorFrame\":[{\"duration\":6,\"tweenEasing\":0},{\"duration\":35,\"value\":{\"aM\":0}}]},{\"name\":\"sbt\",\"displayFrame\":[{\"duration\":4,\"value\":-1},{\"duration\":37}],\"colorFrame\":[{\"duration\":4},{\"duration\":5,\"tweenEasing\":0,\"value\":{\"aM\":0}},{\"duration\":12,\"tweenEasing\":0},{\"duration\":7,\"tweenEasing\":0},{\"duration\":13,\"value\":{\"aM\":0}}]},{\"name\":\"smi\",\"displayFrame\":[{\"duration\":4,\"value\":-1},{\"duration\":37}],\"colorFrame\":[{\"duration\":30},{\"duration\":6,\"tweenEasing\":0},{\"duration\":5,\"value\":{\"aM\":0}}]},{\"name\":\"smo\",\"displayFrame\":[{\"duration\":14,\"value\":-1},{\"duration\":27}],\"colorFrame\":[{\"duration\":30},{\"duration\":6,\"tweenEasing\":0},{\"duration\":5,\"value\":{\"aM\":0}}]},{\"name\":\"smp\",\"displayFrame\":[{\"duration\":4,\"value\":-1},{\"duration\":37}],\"colorFrame\":[{\"duration\":24},{\"duration\":6,\"tweenEasing\":0},{\"duration\":11,\"value\":{\"aM\":0}}]},{\"name\":\"sbh\",\"displayFrame\":[{\"duration\":4,\"value\":-1},{\"duration\":37}],\"colorFrame\":[{\"duration\":4},{\"duration\":5,\"tweenEasing\":0,\"value\":{\"aM\":0}},{\"duration\":12,\"tweenEasing\":0},{\"duration\":7,\"tweenEasing\":0},{\"duration\":13,\"value\":{\"aM\":0}}]},{\"name\":\"bbsL\",\"displayFrame\":[{\"duration\":4,\"value\":-1},{\"duration\":37}],\"colorFrame\":[{\"duration\":4},{\"duration\":3,\"curve\":[0,0,0.5,1],\"value\":{\"aM\":0}},{\"duration\":8,\"tweenEasing\":0},{\"duration\":6,\"tweenEasing\":0},{\"duration\":20,\"value\":{\"aM\":0}}]},{\"name\":\"bbsR\",\"displayFrame\":[{\"duration\":4,\"value\":-1},{\"duration\":37}],\"colorFrame\":[{\"duration\":4},{\"duration\":3,\"curve\":[0,0,0.5,1],\"value\":{\"aM\":0}},{\"duration\":8,\"tweenEasing\":0},{\"duration\":6,\"tweenEasing\":0},{\"duration\":20,\"value\":{\"aM\":0}}]},{\"name\":\"bb1\",\"displayFrame\":[{\"duration\":14,\"value\":-1},{\"duration\":27}],\"colorFrame\":[{\"duration\":30},{\"duration\":7,\"tweenEasing\":0},{\"duration\":4,\"value\":{\"aM\":0}}]},{\"name\":\"bb2\",\"displayFrame\":[{\"duration\":18,\"value\":-1},{\"duration\":23}],\"colorFrame\":[{\"duration\":34},{\"duration\":7,\"tweenEasing\":0},{\"duration\":0,\"value\":{\"aM\":0}}]},{\"name\":\"backU\",\"colorFrame\":[{\"duration\":6,\"tweenEasing\":0},{\"duration\":35,\"value\":{\"aM\":0}}]}]}],\"defaultActions\":[{\"gotoAndPlay\":\"Idle\"}]},{\"type\":\"Armature\",\"frameRate\":30,\"name\":\"_wvD_U\",\"aabb\":{\"x\":-62.54,\"y\":-74.35,\"width\":123,\"height\":151.43},\"bone\":[{\"name\":\"root\"},{\"name\":\"wvL_U\",\"parent\":\"root\",\"transform\":{\"x\":-32.6345,\"y\":14.2619,\"scX\":0.7161,\"scY\":0.7161}},{\"name\":\"wvR_U\",\"parent\":\"root\",\"transform\":{\"x\":28.0537,\"y\":17.9101,\"scX\":0.7161,\"scY\":0.7161}},{\"name\":\"wvB_U\",\"parent\":\"root\",\"transform\":{\"x\":-0.6144,\"y\":-38.2745,\"scX\":0.7161,\"scY\":0.7161}}],\"slot\":[{\"name\":\"wvL_U\",\"parent\":\"wvL_U\"},{\"name\":\"wvR_U\",\"parent\":\"wvR_U\"},{\"name\":\"wvB_U\",\"parent\":\"wvB_U\"}],\"skin\":[{\"slot\":[{\"name\":\"wvR_U\",\"display\":[{\"name\":\"wvR_U\",\"transform\":{\"x\":-6.71,\"y\":4.42,\"skX\":54.15,\"skY\":54.15}}]},{\"name\":\"wvB_U\",\"display\":[{\"name\":\"wvB_U\",\"transform\":{\"x\":-0.6,\"y\":-14.77,\"skX\":178.23,\"skY\":178.23}}]},{\"name\":\"wvL_U\",\"display\":[{\"name\":\"wvL_U\",\"transform\":{\"x\":13.12,\"y\":8.06,\"skX\":-54.43,\"skY\":-54.43}}]}]}],\"animation\":[{\"duration\":35,\"playTimes\":0,\"name\":\"idle\",\"bone\":[{\"name\":\"wvL_U\",\"translateFrame\":[{\"duration\":5},{\"duration\":30,\"curve\":[0.5,0,0.5,1]},{\"duration\":0,\"x\":-11.66,\"y\":-2.05}]},{\"name\":\"wvR_U\",\"translateFrame\":[{\"duration\":5},{\"duration\":30,\"curve\":[0.5,0,0.5,1]},{\"duration\":0,\"x\":12.27,\"y\":-2.82}]},{\"name\":\"wvB_U\",\"translateFrame\":[{\"duration\":5},{\"duration\":30,\"curve\":[0.5,0,0.5,1]},{\"duration\":0,\"x\":-0.3,\"y\":-11.1}]}],\"slot\":[{\"name\":\"wvL_U\",\"displayFrame\":[{\"duration\":5,\"value\":-1},{\"duration\":30}],\"colorFrame\":[{\"duration\":5},{\"duration\":15,\"curve\":[0.5,0,0.5,1],\"value\":{\"aM\":0}},{\"duration\":15,\"curve\":[0.5,0,0.5,1]},{\"duration\":0,\"value\":{\"aM\":0}}]},{\"name\":\"wvR_U\",\"displayFrame\":[{\"duration\":5,\"value\":-1},{\"duration\":30}],\"colorFrame\":[{\"duration\":5},{\"duration\":15,\"curve\":[0.5,0,0.5,1],\"value\":{\"aM\":0}},{\"duration\":15,\"curve\":[0.5,0,0.5,1]},{\"duration\":0,\"value\":{\"aM\":0}}]},{\"name\":\"wvB_U\",\"displayFrame\":[{\"duration\":5,\"value\":-1},{\"duration\":30}],\"colorFrame\":[{\"duration\":5},{\"duration\":15,\"curve\":[0.5,0,0.5,1],\"value\":{\"aM\":0}},{\"duration\":15,\"curve\":[0.5,0,0.5,1]},{\"duration\":0,\"value\":{\"aM\":0}}]}]}],\"defaultActions\":[{\"gotoAndPlay\":\"idle\"}]},{\"type\":\"Armature\",\"frameRate\":30,\"name\":\"_wvD_D\",\"aabb\":{\"x\":-82.55,\"y\":-80.45,\"width\":148.28,\"height\":167.32},\"bone\":[{\"name\":\"root\"},{\"name\":\"wv5\",\"parent\":\"root\",\"transform\":{\"x\":19.8237,\"y\":-68.5535}},{\"name\":\"wv2\",\"parent\":\"root\",\"transform\":{\"x\":-64.4963,\"y\":-52.2376}},{\"name\":\"wv0\",\"parent\":\"root\",\"transform\":{\"x\":58.4697,\"y\":-43.3316}},{\"name\":\"wv01\",\"parent\":\"root\",\"transform\":{\"x\":-45.9657,\"y\":-70.8537}},{\"name\":\"wv\",\"parent\":\"root\",\"transform\":{\"x\":-59.5572,\"y\":19.1326}},{\"name\":\"wv02\",\"parent\":\"root\",\"transform\":{\"x\":60.0358,\"y\":39.5495,\"skX\":31.1343,\"skY\":31.1343}},{\"name\":\"wv03\",\"parent\":\"root\",\"transform\":{\"x\":22.3584,\"y\":76.9983}}],\"slot\":[{\"name\":\"wv5\",\"parent\":\"wv5\"},{\"name\":\"wv2\",\"parent\":\"wv2\"},{\"name\":\"wv0\",\"parent\":\"wv0\"},{\"name\":\"wv01\",\"parent\":\"wv01\"},{\"name\":\"wv\",\"parent\":\"wv\"},{\"name\":\"wv02\",\"parent\":\"wv02\"},{\"name\":\"wv03\",\"parent\":\"wv03\"}],\"skin\":[{\"slot\":[{\"name\":\"wv0\",\"display\":[{\"name\":\"wv0\",\"transform\":{\"x\":-4.54,\"y\":1.35}}]},{\"name\":\"wv5\",\"display\":[{\"name\":\"wv5\",\"transform\":{\"x\":0.01,\"y\":0.17}}]},{\"name\":\"wv2\",\"display\":[{\"name\":\"wv2\",\"transform\":{\"x\":4.29,\"y\":3.5,\"skX\":-32.14,\"skY\":-32.14}}]},{\"name\":\"wv03\",\"display\":[{\"name\":\"wv0\",\"transform\":{\"x\":-1.19,\"y\":-4.13,\"skX\":112.08,\"skY\":112.08,\"scY\":1.4447}}]},{\"name\":\"wv01\",\"display\":[{\"name\":\"wv0\",\"transform\":{\"x\":0.92,\"y\":4.4,\"skX\":-81.69,\"skY\":-81.69}}]},{\"name\":\"wv\",\"display\":[{\"name\":\"wv\",\"transform\":{\"x\":5.5,\"y\":-2.28,\"skX\":-20.69,\"skY\":-20.69,\"scX\":0.6209,\"scY\":0.6209}}]},{\"name\":\"wv02\",\"display\":[{\"name\":\"wv0\",\"transform\":{\"x\":-5.17,\"y\":0.74,\"skX\":23.64,\"skY\":23.64,\"scX\":1.2113,\"scY\":1.2113}}]}]}],\"animation\":[{\"duration\":50,\"playTimes\":0,\"name\":\"idle\",\"bone\":[{\"name\":\"wv5\",\"translateFrame\":[{\"duration\":10},{\"duration\":30,\"curve\":[0.5,0,0.5,1]},{\"duration\":10,\"x\":0.61,\"y\":14.02}]},{\"name\":\"wv2\",\"translateFrame\":[{\"duration\":30,\"curve\":[0.5,0,0.5,1]},{\"duration\":20,\"x\":11.58,\"y\":10.06}]},{\"name\":\"wv0\",\"translateFrame\":[{\"duration\":5,\"curve\":[0,0,0.5,1],\"x\":-11.96,\"y\":2.92},{\"duration\":20,\"tweenEasing\":0,\"x\":-12.5,\"y\":3.05},{\"duration\":25,\"curve\":[0.5,0,1,1]},{\"duration\":0,\"x\":-11.96,\"y\":2.92}]},{\"name\":\"wv01\",\"translateFrame\":[{\"duration\":30,\"curve\":[0.5,0,0.5,1]},{\"duration\":20,\"x\":5.49,\"y\":16.76}]},{\"name\":\"wv\",\"translateFrame\":[{\"duration\":20},{\"duration\":30,\"curve\":[0.5,0,0.5,1]},{\"duration\":0,\"x\":12.19,\"y\":-0.3}]},{\"name\":\"wv02\",\"translateFrame\":[{\"duration\":15,\"curve\":[0,0,0.5,1],\"x\":-8.08,\"y\":0.76},{\"duration\":20,\"tweenEasing\":0,\"x\":-16.16,\"y\":1.52},{\"duration\":15,\"curve\":[0.5,0,1,1]},{\"duration\":0,\"x\":-8.08,\"y\":0.76}]},{\"name\":\"wv03\",\"translateFrame\":[{\"duration\":15},{\"duration\":30,\"curve\":[0.5,0,0.5,1]},{\"duration\":5,\"x\":0.91,\"y\":-18.9}]}],\"slot\":[{\"name\":\"wv5\",\"displayFrame\":[{\"duration\":10,\"value\":-1},{\"duration\":30},{\"duration\":10,\"value\":-1}],\"colorFrame\":[{\"duration\":10},{\"duration\":15,\"curve\":[0.5,0,0.5,1],\"value\":{\"aM\":0}},{\"duration\":15,\"curve\":[0.5,0,0.5,1]},{\"duration\":10,\"value\":{\"aM\":0}}]},{\"name\":\"wv2\",\"displayFrame\":[{\"duration\":30},{\"duration\":20,\"value\":-1}],\"colorFrame\":[{\"duration\":15,\"curve\":[0.5,0,0.5,1],\"value\":{\"aM\":0}},{\"duration\":15,\"curve\":[0.5,0,0.5,1]},{\"duration\":20,\"value\":{\"aM\":0}}]},{\"name\":\"wv0\",\"displayFrame\":[{\"duration\":5},{\"duration\":20,\"value\":-1},{\"duration\":25}],\"colorFrame\":[{\"duration\":5,\"curve\":[0,0,0.5,1],\"value\":{\"aM\":20}},{\"duration\":20,\"tweenEasing\":0,\"value\":{\"aM\":0}},{\"duration\":15,\"curve\":[0.5,0,0.5,1],\"value\":{\"aM\":0}},{\"duration\":10,\"curve\":[0.5,0,1,1]},{\"duration\":0,\"value\":{\"aM\":20}}]},{\"name\":\"wv01\",\"displayFrame\":[{\"duration\":30},{\"duration\":20,\"value\":-1}],\"colorFrame\":[{\"duration\":15,\"curve\":[0.5,0,0.5,1],\"value\":{\"aM\":0}},{\"duration\":15,\"curve\":[0.5,0,0.5,1]},{\"duration\":20,\"value\":{\"aM\":0}}]},{\"name\":\"wv\",\"displayFrame\":[{\"duration\":20,\"value\":-1},{\"duration\":30},{\"duration\":0,\"value\":-1}],\"colorFrame\":[{\"duration\":20},{\"duration\":15,\"curve\":[0.5,0,0.5,1],\"value\":{\"aM\":0}},{\"duration\":15,\"curve\":[0.5,0,0.5,1]},{\"duration\":0,\"value\":{\"aM\":0}}]},{\"name\":\"wv02\",\"displayFrame\":[{\"duration\":15},{\"duration\":20,\"value\":-1},{\"duration\":15}],\"colorFrame\":[{\"duration\":15,\"curve\":[0.5,0,0.5,1]},{\"duration\":20,\"tweenEasing\":0,\"value\":{\"aM\":0}},{\"duration\":15,\"curve\":[0.5,0,0.5,1],\"value\":{\"aM\":0}},{\"duration\":0}]},{\"name\":\"wv03\",\"displayFrame\":[{\"duration\":15,\"value\":-1},{\"duration\":35}],\"colorFrame\":[{\"duration\":15},{\"duration\":15,\"curve\":[0.5,0,0.5,1],\"value\":{\"aM\":0}},{\"duration\":15,\"curve\":[0.5,0,0.5,1]},{\"duration\":5,\"value\":{\"aM\":0}}]}]}],\"defaultActions\":[{\"gotoAndPlay\":\"idle\"}]},{\"type\":\"Armature\",\"frameRate\":30,\"name\":\"_wvU_U\",\"aabb\":{\"x\":-62.56,\"y\":-80.32,\"width\":123,\"height\":144.34},\"bone\":[{\"name\":\"root\"},{\"name\":\"wvL_U\",\"parent\":\"root\",\"transform\":{\"x\":-30.6876,\"y\":-31.2418,\"scX\":0.7345,\"scY\":0.7345}},{\"name\":\"wvR_U\",\"parent\":\"root\",\"transform\":{\"x\":30.7794,\"y\":-24.868,\"scX\":0.7345,\"scY\":0.7345}},{\"name\":\"wvB_U\",\"parent\":\"root\",\"transform\":{\"x\":-0.6144,\"y\":49.37,\"scX\":0.7345,\"scY\":0.7345}}],\"slot\":[{\"name\":\"wvL_U\",\"parent\":\"wvL_U\"},{\"name\":\"wvR_U\",\"parent\":\"wvR_U\"},{\"name\":\"wvB_U\",\"parent\":\"wvB_U\"}],\"skin\":[{\"slot\":[{\"name\":\"wvL_U\",\"display\":[{\"name\":\"wvL_U\",\"transform\":{\"x\":13.12,\"y\":8.06}}]},{\"name\":\"wvR_U\",\"display\":[{\"name\":\"wvR_U\",\"transform\":{\"x\":-6.71,\"y\":4.42}}]},{\"name\":\"wvB_U\",\"display\":[{\"name\":\"wvB_U\",\"transform\":{\"x\":-0.6,\"y\":-14.77}}]}]}],\"animation\":[{\"duration\":35,\"playTimes\":0,\"name\":\"idle\",\"bone\":[{\"name\":\"wvL_U\",\"translateFrame\":[{\"duration\":5},{\"duration\":30,\"curve\":[0.5,0,0.5,1]},{\"duration\":0,\"x\":-10.67,\"y\":-14.94}]},{\"name\":\"wvR_U\",\"translateFrame\":[{\"duration\":5},{\"duration\":30,\"curve\":[0.5,0,0.5,1]},{\"duration\":0,\"x\":15.24,\"y\":-9.75}]},{\"name\":\"wvB_U\",\"translateFrame\":[{\"duration\":5},{\"duration\":30,\"curve\":[0.5,0,0.5,1]},{\"duration\":0,\"x\":-0.3,\"y\":11.06}]}],\"slot\":[{\"name\":\"wvL_U\",\"displayFrame\":[{\"duration\":5,\"value\":-1},{\"duration\":30}],\"colorFrame\":[{\"duration\":5},{\"duration\":15,\"curve\":[0.5,0,0.5,1],\"value\":{\"aM\":0}},{\"duration\":15,\"curve\":[0.5,0,0.5,1]},{\"duration\":0,\"value\":{\"aM\":0}}]},{\"name\":\"wvR_U\",\"displayFrame\":[{\"duration\":5,\"value\":-1},{\"duration\":30}],\"colorFrame\":[{\"duration\":5},{\"duration\":15,\"curve\":[0.5,0,0.5,1],\"value\":{\"aM\":0}},{\"duration\":15,\"curve\":[0.5,0,0.5,1]},{\"duration\":0,\"value\":{\"aM\":0}}]},{\"name\":\"wvB_U\",\"displayFrame\":[{\"duration\":5,\"value\":-1},{\"duration\":30}],\"colorFrame\":[{\"duration\":5},{\"duration\":15,\"curve\":[0.5,0,0.5,1],\"value\":{\"aM\":0}},{\"duration\":15,\"curve\":[0.5,0,0.5,1]},{\"duration\":0,\"value\":{\"aM\":0}}]}]}],\"defaultActions\":[{\"gotoAndPlay\":\"idle\"}]},{\"type\":\"Armature\",\"frameRate\":30,\"name\":\"Up_D\",\"aabb\":{\"x\":-110,\"y\":-110,\"width\":220,\"height\":220},\"bone\":[{\"name\":\"root\"},{\"name\":\"main\",\"parent\":\"root\"}],\"slot\":[{\"name\":\"caveU\",\"parent\":\"main\"},{\"name\":\"_wvU\",\"parent\":\"main\"}],\"skin\":[{\"slot\":[{\"name\":\"caveU\",\"display\":[{\"name\":\"caveU\",\"path\":\"cave\"}]},{\"name\":\"_wvU\",\"display\":[{\"type\":\"armature\",\"name\":\"_wvU\",\"transform\":{\"scX\":0.867,\"scY\":0.867},\"path\":\"_wvU_D\"}]}]}],\"animation\":[{\"duration\":0,\"playTimes\":0,\"name\":\"Idle\"},{\"duration\":41,\"playTimes\":0,\"name\":\"Die\",\"frame\":[{\"duration\":41},{\"duration\":0,\"events\":[{\"name\":\"die\"}]}],\"slot\":[{\"name\":\"caveU\",\"colorFrame\":[{\"duration\":26},{\"duration\":15,\"tweenEasing\":0},{\"duration\":0,\"value\":{\"aM\":0}}]},{\"name\":\"_wvU\",\"colorFrame\":[{\"duration\":26},{\"duration\":15,\"tweenEasing\":0},{\"duration\":0,\"value\":{\"aM\":0}}]}]}],\"defaultActions\":[{\"gotoAndPlay\":\"Idle\"}]},{\"type\":\"Armature\",\"frameRate\":30,\"name\":\"Down_D\",\"aabb\":{\"x\":-110,\"y\":-110,\"width\":220,\"height\":220},\"bone\":[{\"name\":\"root\"},{\"name\":\"main\",\"parent\":\"root\"}],\"slot\":[{\"name\":\"caveU\",\"parent\":\"main\"},{\"name\":\"_wvD_D\",\"parent\":\"main\"}],\"skin\":[{\"slot\":[{\"name\":\"caveU\",\"display\":[{\"name\":\"caveU\",\"path\":\"cave\"}]},{\"name\":\"_wvD_D\",\"display\":[{\"type\":\"armature\",\"name\":\"_wvD_D\",\"transform\":{\"scX\":0.8611,\"scY\":0.8611}}]}]}],\"animation\":[{\"duration\":0,\"playTimes\":0,\"name\":\"Idle\"},{\"duration\":41,\"playTimes\":0,\"name\":\"Die\",\"frame\":[{\"duration\":4},{\"duration\":37,\"events\":[{\"name\":\"splash\"}]},{\"duration\":0,\"events\":[{\"name\":\"die\"}]}],\"slot\":[{\"name\":\"caveU\",\"colorFrame\":[{\"duration\":26},{\"duration\":15,\"tweenEasing\":0},{\"duration\":0,\"value\":{\"aM\":0}}]}]}],\"defaultActions\":[{\"gotoAndPlay\":\"Idle\"}]}]}"]],0,0,[],[],[]],[[[11,"TileAnimate_tex","{\"width\":1024,\"SubTexture\":[{\"frameX\":-2,\"y\":913,\"frameY\":-2,\"frameWidth\":76,\"width\":72,\"frameHeight\":95,\"height\":91,\"name\":\"sinkFaceU\",\"x\":314},{\"frameX\":-2,\"y\":913,\"frameY\":-2,\"frameWidth\":72,\"width\":68,\"frameHeight\":99,\"height\":95,\"name\":\"bottom_U\",\"x\":458},{\"frameX\":-2,\"y\":913,\"frameY\":-2,\"frameWidth\":72,\"width\":68,\"frameHeight\":99,\"height\":95,\"name\":\"faceU\",\"x\":388},{\"frameX\":-2,\"y\":969,\"frameY\":-2,\"frameWidth\":133,\"width\":128,\"frameHeight\":39,\"height\":35,\"name\":\"sinkBottom\",\"x\":122},{\"frameX\":-2,\"y\":1006,\"frameY\":-2,\"frameWidth\":131,\"width\":122,\"frameHeight\":21,\"height\":17,\"name\":\"sinkBottomSide\",\"x\":122},{\"frameX\":-2,\"y\":1,\"frameY\":-2,\"frameWidth\":421,\"width\":417,\"frameHeight\":356,\"height\":352,\"name\":\"tide/splash_baseThere\",\"x\":603},{\"frameX\":-2,\"y\":1,\"frameY\":-2,\"frameWidth\":292,\"width\":287,\"frameHeight\":530,\"height\":526,\"name\":\"tide/splashMainInner\",\"x\":314},{\"frameX\":-4,\"y\":503,\"frameY\":-2,\"frameWidth\":338,\"width\":311,\"frameHeight\":482,\"height\":464,\"name\":\"tide/splashMainOuter\",\"x\":1},{\"frameX\":-4,\"y\":1,\"frameY\":-2,\"frameWidth\":338,\"width\":311,\"frameHeight\":528,\"height\":500,\"name\":\"tide/splashMainPush\",\"x\":1},{\"frameX\":-2,\"y\":355,\"frameY\":-2,\"frameWidth\":360,\"width\":356,\"frameHeight\":179,\"height\":175,\"name\":\"tide/splash_baseHere\",\"x\":603},{\"frameX\":-2,\"y\":747,\"frameY\":-2,\"frameWidth\":195,\"width\":190,\"frameHeight\":87,\"height\":82,\"name\":\"tide/splash_bubblesL\",\"x\":314},{\"frameX\":-2,\"y\":831,\"frameY\":-2,\"frameWidth\":185,\"width\":180,\"frameHeight\":85,\"height\":80,\"name\":\"tide/splash_bubblesR\",\"x\":314},{\"frameX\":-2,\"y\":831,\"frameY\":-2,\"frameWidth\":40,\"width\":35,\"frameHeight\":36,\"height\":31,\"name\":\"tide/splash_bubble1\",\"x\":496},{\"frameX\":-2,\"y\":969,\"frameY\":-2,\"frameWidth\":55,\"width\":50,\"frameHeight\":50,\"height\":45,\"name\":\"tide/splash_bubble2\",\"x\":252},{\"frameX\":-2,\"y\":1006,\"frameY\":-2,\"frameWidth\":46,\"width\":42,\"frameHeight\":16,\"height\":12,\"name\":\"wv5\",\"x\":304},{\"frameX\":-2,\"y\":864,\"frameY\":-2,\"frameWidth\":26,\"width\":22,\"frameHeight\":30,\"height\":26,\"name\":\"wv2\",\"x\":496},{\"frameX\":-2,\"y\":864,\"frameY\":-2,\"frameWidth\":21,\"width\":17,\"frameHeight\":28,\"height\":24,\"name\":\"wv0\",\"x\":520},{\"frameX\":-2,\"y\":355,\"frameY\":-2,\"frameWidth\":57,\"width\":53,\"frameHeight\":110,\"height\":105,\"name\":\"wv\",\"x\":961},{\"frameX\":-2,\"y\":913,\"frameY\":-2,\"frameWidth\":72,\"width\":68,\"frameHeight\":99,\"height\":94,\"name\":\"faceD\",\"x\":528},{\"frameX\":-2,\"y\":529,\"frameY\":-2,\"frameWidth\":68,\"width\":64,\"frameHeight\":110,\"height\":106,\"name\":\"wvL_U\",\"x\":532},{\"frameX\":-2,\"y\":462,\"frameY\":-2,\"frameWidth\":55,\"width\":51,\"frameHeight\":112,\"height\":108,\"name\":\"wvR_U\",\"x\":961},{\"frameX\":-2,\"y\":969,\"frameY\":-2,\"frameWidth\":123,\"width\":119,\"frameHeight\":51,\"height\":47,\"name\":\"wvB_U\",\"x\":1},{\"frameX\":-2,\"y\":529,\"frameY\":-2,\"frameWidth\":220,\"width\":216,\"frameHeight\":220,\"height\":216,\"name\":\"cave\",\"x\":314}],\"height\":1024,\"name\":\"TileAnimate\",\"imagePath\":\"TileAnimate_tex.png\"}",{"width":1024,"height":1024,"name":"TileAnimate","imagePath":"TileAnimate_tex.png","SubTexture":[{"frameX":-2,"y":913,"frameY":-2,"frameWidth":76,"width":72,"frameHeight":95,"height":91,"name":"sinkFaceU","x":314},{"frameX":-2,"y":913,"frameY":-2,"frameWidth":72,"width":68,"frameHeight":99,"height":95,"name":"bottom_U","x":458},{"frameX":-2,"y":913,"frameY":-2,"frameWidth":72,"width":68,"frameHeight":99,"height":95,"name":"faceU","x":388},{"frameX":-2,"y":969,"frameY":-2,"frameWidth":133,"width":128,"frameHeight":39,"height":35,"name":"sinkBottom","x":122},{"frameX":-2,"y":1006,"frameY":-2,"frameWidth":131,"width":122,"frameHeight":21,"height":17,"name":"sinkBottomSide","x":122},{"frameX":-2,"y":1,"frameY":-2,"frameWidth":421,"width":417,"frameHeight":356,"height":352,"name":"tide/splash_baseThere","x":603},{"frameX":-2,"y":1,"frameY":-2,"frameWidth":292,"width":287,"frameHeight":530,"height":526,"name":"tide/splashMainInner","x":314},{"frameX":-4,"y":503,"frameY":-2,"frameWidth":338,"width":311,"frameHeight":482,"height":464,"name":"tide/splashMainOuter","x":1},{"frameX":-4,"y":1,"frameY":-2,"frameWidth":338,"width":311,"frameHeight":528,"height":500,"name":"tide/splashMainPush","x":1},{"frameX":-2,"y":355,"frameY":-2,"frameWidth":360,"width":356,"frameHeight":179,"height":175,"name":"tide/splash_baseHere","x":603},{"frameX":-2,"y":747,"frameY":-2,"frameWidth":195,"width":190,"frameHeight":87,"height":82,"name":"tide/splash_bubblesL","x":314},{"frameX":-2,"y":831,"frameY":-2,"frameWidth":185,"width":180,"frameHeight":85,"height":80,"name":"tide/splash_bubblesR","x":314},{"frameX":-2,"y":831,"frameY":-2,"frameWidth":40,"width":35,"frameHeight":36,"height":31,"name":"tide/splash_bubble1","x":496},{"frameX":-2,"y":969,"frameY":-2,"frameWidth":55,"width":50,"frameHeight":50,"height":45,"name":"tide/splash_bubble2","x":252},{"frameX":-2,"y":1006,"frameY":-2,"frameWidth":46,"width":42,"frameHeight":16,"height":12,"name":"wv5","x":304},{"frameX":-2,"y":864,"frameY":-2,"frameWidth":26,"width":22,"frameHeight":30,"height":26,"name":"wv2","x":496},{"frameX":-2,"y":864,"frameY":-2,"frameWidth":21,"width":17,"frameHeight":28,"height":24,"name":"wv0","x":520},{"frameX":-2,"y":355,"frameY":-2,"frameWidth":57,"width":53,"frameHeight":110,"height":105,"name":"wv","x":961},{"frameX":-2,"y":913,"frameY":-2,"frameWidth":72,"width":68,"frameHeight":99,"height":94,"name":"faceD","x":528},{"frameX":-2,"y":529,"frameY":-2,"frameWidth":68,"width":64,"frameHeight":110,"height":106,"name":"wvL_U","x":532},{"frameX":-2,"y":462,"frameY":-2,"frameWidth":55,"width":51,"frameHeight":112,"height":108,"name":"wvR_U","x":961},{"frameX":-2,"y":969,"frameY":-2,"frameWidth":123,"width":119,"frameHeight":51,"height":47,"name":"wvB_U","x":1},{"frameX":-2,"y":529,"frameY":-2,"frameWidth":220,"width":216,"frameHeight":220,"height":216,"name":"cave","x":314}]}]],0,0,[0],[6],[7]],[[[1,"splash1",".mp3",2.052],-1],0,0,[],[],[]],[[[1,"splash0",".mp3",1.548],-1],0,0,[],[],[]]]]
